Workbook

Sheet Feuil1
A1: Année | B1: 2026 | D1: Jour férie | E1: Valeur retour
D2: =DATE($B$1,1,1) -> 46023 | E2: Oui
D3: =FLOOR(DAY(MINUTE($B$1/38)/2+56)&"/5/"&$B$1,7)-34 -> 46117 | E3: Oui
D4: =D3 + 1 -> 46118 | E4: Oui
D5: =DATE($B$1,5,1) -> 46143 | E5: Oui
D6: =DATE($B$1,5,8) -> 46150 | E6: Oui
D7: =D3+"39" -> 46156 | E7: Oui
D8: =D3 + 49 -> 46166 | E8: Oui
D9: =D3 + 50 -> 46167 | E9: Oui
D10: =DATE($B$1,7,14) -> 46217 | E10: Oui
D11: =DATE($B$1,8,15) -> 46249 | E11: Oui
D12: =DATE($B$1,11,1) -> 46327 | E12: Oui
D13: =DATE($B$1,11,11) -> 46337 | E13: Oui
D14: =DATE($B$1,12,25) -> 46381 | E14: Oui
D15: 46023 | E15: Oui

Sheet AVRIL 2026
A1: CALENDRIER CLOTURE AVRIL 2026
A2: ARRETE | B2: TRAITEMENT | C2: RESTITUTION | D2: Date de Référence J
A3: Date limite de remontée des PV pour mise en service des investissements | E3: =IF(G3="J",D3,WORKDAY(D$48,MID(G3,2,3),Feuil1!D$2:D$14)) -> 46132 | F3: Matin | G3: J-8
A4: Premiers relevés de compteurs et de stocks | E4: =IF(G4="J",D4,WORKDAY(D$48,MID(G4,2,3),Feuil1!D$2:D$14)) -> 46133 | F4: Matin | G4: J-7
B5: Incorporation en comptabilité des écritures GL de paie | E5: =IF(G5="J",D5,WORKDAY(D$48,MID(G5,2,3),Feuil1!D$2:D$14)) -> 46134 | F5: Nuit | G5: J-6
C6: Campagne Fournisseurs TIERS FDM - Mise à disposition des échéanciers provisoires | E6: =IF(G6="J",D6,WORKDAY(D$48,MID(G6,2,3),Feuil1!D$2:D$14)) -> 46135 | F6: Matin | G6: J-5
A7: ARCAS | B7: Envoi à la compta Siège du fichier PROGEFI par le service Trésorerie incluant les remarques des Uos | E7: =IF(G7="J",D7,WORKDAY(D$48,MID(G7,2,3),Feuil1!D$2:D$14)) -> 46135 | F7: Matin | G7: J-5
A8: Fermeture du livre comptable FA | E8: =IF(G8="J",D8,WORKDAY(D$48,MID(G8,2,3),Feuil1!D$2:D$14)) -> 46135 | F8: Soir | G8: J-5
B9: Premier passage des abonnements GL dans Oracle | E9: =IF(G9="J",D9,WORKDAY(D$48,MID(G9,2,3),Feuil1!D$2:D$14)) -> 46135 | F9: Nuit | G9: J-5
B10: Incorporation des écritures d'amortissements | E10: =IF(G10="J",D10,WORKDAY(D$48,MID(G10,2,3),Feuil1!D$2:D$14)) -> 46135 | F10: Nuit | G10: J-5
B11: Incorporation en comptabilité des écritures GL et provisions DACAR | E11: =IF(G11="J",D11,WORKDAY(D$48,MID(G11,2,3),Feuil1!D$2:D$14)) -> 46135 | F11: Nuit | G11: J-5
A12: Campagne Fournisseurs TIERS FDM - Mise à disposition des pupitres et envoi du mail de Projection | E12: =IF(G12="J",D12,WORKDAY(D$48,MID(G12,2,3),Feuil1!D$2:D$14)) -> 46136 | F12: Matin | G12: J-4
A13: Date limite d'intégration des factures de carburant et péages (DACAR) | E13: =IF(G13="J",D13,WORKDAY(D$48,MID(G13,2,3),Feuil1!D$2:D$14)) -> 46136 | F13: Journée | G13: J-4
A14: CALLISTO | B14: Derniers retours des Uos (mise à jour navettes : subventions, exceptions) et remarques sur traitement M-1 | E14: =IF(G14="J",D14,WORKDAY(D$48,MID(G14,2,3),Feuil1!D$2:D$14)) -> 46136 | F14: Soir | G14: J-4
A15: ARCAS | B15: Traitement ARCAS pour incorporation des écritures d'abonnement | E15: =IF(G15="J",D15,WORKDAY(D$48,MID(G15,2,3),Feuil1!D$2:D$14)) -> 46136 | F15: Soir | G15: J-4
A16: Dernières transmissions des heures de M.O. | E16: =IF(G16="J",D16,WORKDAY(D$48,MID(G16,2,3),Feuil1!D$2:D$14)) -> 46136 | F16: Soir | G16: J-4
A17: Dernières saisies et validation des relevés de compteur et de stocks et des livraisons | E17: =IF(G17="J",D17,WORKDAY(D$48,MID(G17,2,3),Feuil1!D$2:D$14)) -> 46136 | F17: Soir | G17: J-4
A18: Validation de l'échéancier TIERS FDM + Envoi des ordres de virements à CDPG + Envoi des avis de virements par mail aux Frs | E18: =IF(G18="J",D18,WORKDAY(D$48,MID(G18,2,3),Feuil1!D$2:D$14)) -> 46136 | F18: Soir | G18: J-4
B19: Second passage des abonnements GL dans Oracle | E19: =IF(G19="J",D19,WORKDAY(D$48,MID(G19,2,3),Feuil1!D$2:D$14)) -> 46136 | F19: Nuit | G19: J-4
B20: Calcul de la M.O. au THO (VACHE) | E20: =IF(G20="J",D20,WORKDAY(D$48,MID(G20,2,3),Feuil1!D$2:D$14)) -> 46136 | F20: Nuit | G20: J-4
C21: Envoi du mail de confirmation des virements TIERS FDM | E21: =IF(G21="J",D21,WORKDAY(D$48,MID(G21,2,3),Feuil1!D$2:D$14)) -> 46139 | F21: Matin | G21: J-3
A22: CALLISTO | B22: Traitement CALLISTO et incorporation des écritures IFRS + envoi fichiers justificatifs aux Uos | E22: =IF(G22="J",D22,WORKDAY(D$48,MID(G22,2,3),Feuil1!D$2:D$14)) -> 46139 | F22: Soir | G22: J-3
A23: ARCAS | B23: Traitement ARCAS et incorporation des écritures IFRS + envoi fichiers justificatifs aux Uos | E23: =IF(G23="J",D23,WORKDAY(D$48,MID(G23,2,3),Feuil1!D$2:D$14)) -> 46139 | F23: Soir | G23: J-3
A24: Arrêté ventes travaux (CITY) | E24: =IF(G24="J",D24,WORKDAY(D$48,MID(G24,2,3),Feuil1!D$2:D$14)) -> 46139 | F24: Soir | G24: J-3
A25: Délai pour la clôture des taches GT,GX et GS | E25: =IF(G25="J",D25,WORKDAY(D$48,MID(G25,2,3),Feuil1!D$2:D$14)) -> 46139 | F25: Soir | G25: J-3
A26: Arrêté ventes exploitation | E26: =IF(G26="J",D26,WORKDAY(D$48,MID(G26,2,3),Feuil1!D$2:D$14)) -> 46139 | F26: Soir | G26: J-3
A27: Arrêté de saisie des factures Open Portal Campus | E27: =IF(G27="J",D27,WORKDAY(D$48,MID(G27,2,3),Feuil1!D$2:D$14)) -> 46139 | F27: Soir | G27: J-3
B28: Calcul des PAR CID | E28: =IF(G28="J",D28,WORKDAY(D$48,MID(G28,2,3),Feuil1!D$2:D$14)) -> 46139 | F28: Soir | G28: J-3
A29: Arrêté de saisie des factures energies | E29: =IF(G29="J",D29,WORKDAY(D$48,MID(G29,2,3),Feuil1!D$2:D$14)) -> 46139 | F29: Soir | G29: J-3
B30: Refacturation intra-groupe premier traitement | E30: =IF(G30="J",D30,WORKDAY(D$48,MID(G30,2,3),Feuil1!D$2:D$14)) -> 46139 | F30: Nuit | G30: J-3
B31: Dernier passage des abonnements GL dans Oracle | E31: =IF(G31="J",D31,WORKDAY(D$48,MID(G31,2,3),Feuil1!D$2:D$14)) -> 46139 | F31: Nuit | G31: J-3
B32: Incorporation des écritures de M.O. | E32: =IF(G32="J",D32,WORKDAY(D$48,MID(G32,2,3),Feuil1!D$2:D$14)) -> 46139 | F32: Nuit | G32: J-3
B33: Traitement PIRENE (calcul des CAP, valorisation des stocks, ventes) | E33: =IF(G33="J",D33,WORKDAY(D$48,MID(G33,2,3),Feuil1!D$2:D$14)) -> 46139 | F33: Nuit | G33: J-3
B34: Calcul des CAP Gaz, Chaleur et électricité CELERIS | E34: =IF(G34="J",D34,WORKDAY(D$48,MID(G34,2,3),Feuil1!D$2:D$14)) -> 46139 | F34: Nuit | G34: J-3
C35: Mise à disposition des états de REFAC au format PDF sur le drive pour les régions | E35: =IF(G35="J",D35,WORKDAY(D$48,MID(G35,2,3),Feuil1!D$2:D$14)) -> 46140 | F35: Matin | G35: J-2
A36: Modification manuelle des PAR Exploitation mensuels CID et CAP Céleris | E36: =IF(G36="J",D36,WORKDAY(D$48,MID(G36,2,3),Feuil1!D$2:D$14)) -> 46140 | F36: Journée | G36: J-2
B37: Génération des écritures des PAR Exploitation mensuels CID | E37: =IF(G37="J",D37,WORKDAY(D$48,MID(G37,2,3),Feuil1!D$2:D$14)) -> 46140 | F37: 17H | G37: J-2
B38: Génération des écritures de CAP CELERIS | E38: =IF(G38="J",D38,WORKDAY(D$48,MID(G38,2,3),Feuil1!D$2:D$14)) -> 46140 | F38: 17H | G38: J-2
B39: Incorporation des écritures de PAR Exploitation mensuels CID | E39: =IF(G39="J",D39,WORKDAY(D$48,MID(G39,2,3),Feuil1!D$2:D$14)) -> 46140 | F39: Nuit | G39: J-2
B40: Incorporation des écritures PIRENE (calcul des CAP, valorisation des stocks, ventes) | E40: =IF(G40="J",D40,WORKDAY(D$48,MID(G40,2,3),Feuil1!D$2:D$14)) -> 46140 | F40: Nuit | G40: J-2
B41: Incorporation des écritures de CAP Gaz, Chaleur et électricité CELERIS | E41: =IF(G41="J",D41,WORKDAY(D$48,MID(G41,2,3),Feuil1!D$2:D$14)) -> 46140 | F41: Nuit | G41: J-2
B42: Refacturation intra-groupe Deuxième traitement | E42: =IF(G42="J",D42,WORKDAY(D$48,MID(G42,2,3),Feuil1!D$2:D$14)) -> 46140 | F42: Nuit | G42: J-2
C43: Mise disposition du fichier Harry Energy | E43: =IF(G43="J",D43,WORKDAY(D$48,MID(G43,2,3),Feuil1!D$2:D$14)) -> 46140 | F43: Nuit | G43: J-2
C44: Mise à disposition des états de REFAC au format PDF sur le drive pour les régions | E44: =IF(G44="J",D44,WORKDAY(D$48,MID(G44,2,3),Feuil1!D$2:D$14)) -> 46141 | F44: Matin | G44: J-1
B45: Fermeture automatique des commandes liées aux factures intra groupe CITY du mois | E45: =IF(G45="J",D45,WORKDAY(D$48,MID(G45,2,3),Feuil1!D$2:D$14)) -> 46141 | F45: Matin | G45: J-1
B46: Refacturation intra-groupe Troisième traitement | E46: =IF(G46="J",D46,WORKDAY(D$48,MID(G46,2,3),Feuil1!D$2:D$14)) -> 46141 | F46: Nuit | G46: J-1
C47: Mise à disposition des états de REFAC au format PDF sur le drive pour les régions | D47: 46142 | E47: =IF(G47="J",D47,WORKDAY(D$48,MID(G47,2,3),Feuil1!D$2:D$14)) -> 46142 | F47: Matin | G47: J
A48: FERMETURE DE L'APPLICATION - CLOTURE PROVISOIRE GL - DEFINITIVES : AP - AR - PO | D48: 46142 | E48: =IF(G48="J",D48,WORKDAY(D$48,MID(G48,2,3),Feuil1!D$2:D$14)) -> 46142 | F48: Nuit | G48: J
B49: Refacturation intra-groupe (dernier passage) | D49: 46142 | E49: =IF(G49="J",D49,WORKDAY(D$48,MID(G49,2,3),Feuil1!D$2:D$14)) -> 46142 | F49: Nuit | G49: J
B50: Calcul des CAP fournisseurs et incorporation des écritures | D50: 46142 | E50: =IF(G50="J",D50,WORKDAY(D$48,MID(G50,2,3),Feuil1!D$2:D$14)) -> 46142 | F50: Nuit | G50: J
B51: Calcul des CAP spécifiques aux contrats de sous traitance et incorporation des écritures | D51: 46142 | E51: =IF(G51="J",D51,WORKDAY(D$48,MID(G51,2,3),Feuil1!D$2:D$14)) -> 46142 | F51: Nuit | G51: J
B52: Calcul et écriture des TEC et PCA (codes R) travaux en cours - produits constatés d'avance | D52: 46142 | E52: =IF(G52="J",D52,WORKDAY(D$48,MID(G52,2,3),Feuil1!D$2:D$14)) -> 46142 | F52: Nuit | G52: J
B53: Calcul et écriture des charges d'avance sur sinistres | D53: 46142 | E53: =IF(G53="J",D53,WORKDAY(D$48,MID(G53,2,3),Feuil1!D$2:D$14)) -> 46142 | F53: Nuit | G53: J
B54: Equilibrage comptable par centre de gestion | D54: 46142 | E54: =IF(G54="J",D54,WORKDAY(D$48,MID(G54,2,3),Feuil1!D$2:D$14)) -> 46142 | F54: Nuit | G54: J
C55: Mise à disposition des états de REFAC au format PDF sur le drive pour les régions | E55: =IF(G55="J",D55,WORKDAY(D$48,MID(G55,2,3),Feuil1!D$2:D$14)) -> 46146 | F55: Matin | G55: J+1
C56: Mise à disposition des états de TVA (AP, AR) sur le drive pour les régions | E56: =IF(G56="J",D56,WORKDAY(D$48,MID(G56,2,3),Feuil1!D$2:D$14)) -> 46146 | F56: Matin | G56: J+1
C57: Mise à disposition des états CAP PO et CAP SSTR sur le drive pour les régions | E57: =IF(G57="J",D57,WORKDAY(D$48,MID(G57,2,3),Feuil1!D$2:D$14)) -> 46146 | F57: Matin | G57: J+1
B58: Imputation (posting) des écritures GL saisies dans la matinée | E58: =IF(G58="J",D58,WORKDAY(D$48,MID(G58,2,3),Feuil1!D$2:D$14)) -> 46146 | F58: 13H | G58: J+1
B59: Extourne des écritures de TEC et PCA travaux en cours - produits constatés d'avance | E59: =IF(G59="J",D59,WORKDAY(D$48,MID(G59,2,3),Feuil1!D$2:D$14)) -> 46146 | F59: Nuit | G59: J+1
B60: Extourne des écritures de charges d'avance sur sinistres | E60: =IF(G60="J",D60,WORKDAY(D$48,MID(G60,2,3),Feuil1!D$2:D$14)) -> 46146 | F60: Nuit | G60: J+1
B61: Imputation (posting) des écritures GL saisies dans la matinée | E61: =IF(G61="J",D61,WORKDAY(D$48,MID(G61,2,3),Feuil1!D$2:D$14)) -> 46147 | F61: 13H | G61: J+2
A62: CLOTURE DEFINITIVE DE GL | E62: =IF(G62="J",D62,WORKDAY(D$48,MID(G62,2,3),Feuil1!D$2:D$14)) -> 46147 | F62: 19H | G62: J+2
B63: Equilibrage comptable par centre de gestion | E63: =IF(G63="J",D63,WORKDAY(D$48,MID(G63,2,3),Feuil1!D$2:D$14)) -> 46148 | F63: Nuit | G63: J+3
B64: Alimentation de la Garantie Totale | E64: =IF(G64="J",D64,WORKDAY(D$48,MID(G64,2,3),Feuil1!D$2:D$14)) -> 46148 | F64: Nuit | G64: J+3
C65: Mise à disposition des états de TVA (GL) sur le drive pour les régions | E65: =IF(G65="J",D65,WORKDAY(D$48,MID(G65,2,3),Feuil1!D$2:D$14)) -> 46148 | F65: Matin | G65: J+3
C66: Mise à disposition des flux et soldes | E66: =IF(G66="J",D66,WORKDAY(D$48,MID(G66,2,3),Feuil1!D$2:D$14)) -> 46148 | F66: Matin | G66: J+3
C67: Mise à disposition de l'état de contrôle des retraitements IFRS | E67: =IF(G67="J",D67,WORKDAY(D$48,MID(G67,2,3),Feuil1!D$2:D$14)) -> 46148 | F67: Matin | G67: J+3
C68: Mise à disposition du fichier d'alimentation de Magnitude sur le drive pour les régions | E68: =IF(G68="J",D68,WORKDAY(D$48,MID(G68,2,3),Feuil1!D$2:D$14)) -> 46148 | F68: Matin | G68: J+3
B69: Incorporation des écritures à contrepassation sur mois suivant (2ème vendredi de chaque mois) | E69: 46150 | F69: Nuit
C70: Mise à disposition des échéanciers provisoires GROUPE sur vos clés régions | E70: =IF(G70="J",D70,WORKDAY(D$48,MID(G70,2,3),Feuil1!D$2:D$14)) -> 46161 | F70: Matin | G70: J+10
A71: Validation de l'échéancier GROUPE + Envoi des ordres de virements à CDPG + Envoi des avis de virements par mail aux Frs | E71: =IF(G71="J",D71,WORKDAY(D$48,MID(G71,2,3),Feuil1!D$2:D$14)) -> 46161 | F71: Soir | G71: J+10
B72: PO Fermeture automatique des commandes (15 du mois) | E72: 46157 | F72: Nuit
C73: Mise à disposition des commandes fermées dans le drive pour les régions | E73: =IF(G73="J",D73,WORKDAY(D$48,MID(G73,2,3),Feuil1!D$2:D$14)) -> 46162 | F73: Matin | G73: J+11
C74: Envoi du mail de confirmation des virements fournisseurs GROUPE | E74: =IF(G74="J",D74,WORKDAY(D$48,MID(G74,2,3),Feuil1!D$2:D$14)) -> 46162 | F74: Matin | G74: J+11
B75: Incorporation des encaissements suite à échéancier Groupe | E75: =IF(G75="J",D75,WORKDAY(D$48,MID(G75,2,3),Feuil1!D$2:D$14)) -> 46162 | F75: Nuit | G75: J+11

Sheet Feuil2
C4: CALENDRIER CLOTURE Avril 2026
C5: Jour | F5: Jalon | G5: Astreinte | H5: Cockpit
C6: Jeudi 23 avril | D6: Nuit | E6: J-5 | F6: Cloture FA
C7: Jeudi 30 avril | D7: Nuit | E7: J | F7: Cloture provisoire | G7: Oui (CtrlM)
C8: Lundi 04 Mai | D8: Matin | E8: J+1 | H8: 8H30
C9: Mardi 05 Mai | D9: Nuit | E9: J+2 | F9: Cloture définitive | G9: Oui (CtrlM)
C10: Mercredi 06 Mai | D10: Matin | E10: J+3 | H10: 8H30

Sheet MAI 2026
A1: CALENDRIER CLOTURE MAI 2026
A2: ARRETE | B2: TRAITEMENT | C2: RESTITUTION | D2: Date de Référence J
A3: Date limite de remontée des PV pour mise en service des investissements | E3: =IF(G3="J",D3,WORKDAY(D$48,MID(G3,2,3),Feuil1!D$2:D$14)) -> 46160 | F3: Matin | G3: J-8
A4: Premiers relevés de compteurs et de stocks | E4: =IF(G4="J",D4,WORKDAY(D$48,MID(G4,2,3),Feuil1!D$2:D$14)) -> 46161 | F4: Matin | G4: J-7
B5: Incorporation en comptabilité des écritures GL de paie | E5: =IF(G5="J",D5,WORKDAY(D$48,MID(G5,2,3),Feuil1!D$2:D$14)) -> 46163 | F5: Nuit | G5: J-5
C6: Campagne Fournisseurs TIERS FDM - Mise à disposition des échéanciers provisoires | E6: =IF(G6="J",D6,WORKDAY(D$48,MID(G6,2,3),Feuil1!D$2:D$14)) -> 46163 | F6: Matin | G6: J-5
A7: ARCAS | B7: Envoi à la compta Siège du fichier PROGEFI par le service Trésorerie incluant les remarques des Uos | E7: =IF(G7="J",D7,WORKDAY(D$48,MID(G7,2,3),Feuil1!D$2:D$14)) -> 46163 | F7: Matin | G7: J-5
A8: Fermeture du livre comptable FA | E8: =IF(G8="J",D8,WORKDAY(D$48,MID(G8,2,3),Feuil1!D$2:D$14)) -> 46163 | F8: Soir | G8: J-5
B9: Premier passage des abonnements GL dans Oracle | E9: =IF(G9="J",D9,WORKDAY(D$48,MID(G9,2,3),Feuil1!D$2:D$14)) -> 46163 | F9: Nuit | G9: J-5
B10: Incorporation des écritures d'amortissements | E10: =IF(G10="J",D10,WORKDAY(D$48,MID(G10,2,3),Feuil1!D$2:D$14)) -> 46163 | F10: Nuit | G10: J-5
B11: Incorporation en comptabilité des écritures GL et provisions DACAR | E11: =IF(G11="J",D11,WORKDAY(D$48,MID(G11,2,3),Feuil1!D$2:D$14)) -> 46163 | F11: Nuit | G11: J-5
A12: Campagne Fournisseurs TIERS FDM - Mise à disposition des pupitres et envoi du mail de Projection | E12: =IF(G12="J",D12,WORKDAY(D$48,MID(G12,2,3),Feuil1!D$2:D$14)) -> 46164 | F12: Matin | G12: J-4
A13: Date limite d'intégration des factures de carburant et péages (DACAR) | E13: =IF(G13="J",D13,WORKDAY(D$48,MID(G13,2,3),Feuil1!D$2:D$14)) -> 46164 | F13: Journée | G13: J-4
A14: CALLISTO | B14: Derniers retours des Uos (mise à jour navettes : subventions, exceptions) et remarques sur traitement M-1 | E14: =IF(G14="J",D14,WORKDAY(D$48,MID(G14,2,3),Feuil1!D$2:D$14)) -> 46164 | F14: Soir | G14: J-4
A15: ARCAS | B15: Traitement ARCAS pour incorporation des écritures d'abonnement | E15: =IF(G15="J",D15,WORKDAY(D$48,MID(G15,2,3),Feuil1!D$2:D$14)) -> 46164 | F15: Soir | G15: J-4
A16: Dernières transmissions des heures de M.O. | E16: =IF(G16="J",D16,WORKDAY(D$48,MID(G16,2,3),Feuil1!D$2:D$14)) -> 46164 | F16: Soir | G16: J-4
A17: Dernières saisies et validation des relevés de compteur et de stocks et des livraisons | E17: =IF(G17="J",D17,WORKDAY(D$48,MID(G17,2,3),Feuil1!D$2:D$14)) -> 46164 | F17: Soir | G17: J-4
A18: Validation de l'échéancier TIERS FDM + Envoi des ordres de virements à CDPG + Envoi des avis de virements par mail aux Frs | E18: =IF(G18="J",D18,WORKDAY(D$48,MID(G18,2,3),Feuil1!D$2:D$14)) -> 46164 | F18: Soir | G18: J-4
B19: Second passage des abonnements GL dans Oracle | E19: =IF(G19="J",D19,WORKDAY(D$48,MID(G19,2,3),Feuil1!D$2:D$14)) -> 46164 | F19: Nuit | G19: J-4
B20: Calcul de la M.O. au THO (VACHE) | E20: =IF(G20="J",D20,WORKDAY(D$48,MID(G20,2,3),Feuil1!D$2:D$14)) -> 46164 | F20: Nuit | G20: J-4
C21: Envoi du mail de confirmation des virements TIERS FDM | E21: =IF(G21="J",D21,WORKDAY(D$48,MID(G21,2,3),Feuil1!D$2:D$14)) -> 46168 | F21: Matin | G21: J-3
A22: CALLISTO | B22: Traitement CALLISTO et incorporation des écritures IFRS + envoi fichiers justificatifs aux Uos | E22: =IF(G22="J",D22,WORKDAY(D$48,MID(G22,2,3),Feuil1!D$2:D$14)) -> 46168 | F22: Soir | G22: J-3
A23: ARCAS | B23: Traitement ARCAS et incorporation des écritures IFRS + envoi fichiers justificatifs aux Uos | E23: =IF(G23="J",D23,WORKDAY(D$48,MID(G23,2,3),Feuil1!D$2:D$14)) -> 46168 | F23: Soir | G23: J-3
A24: Arrêté ventes travaux (CITY) | E24: =IF(G24="J",D24,WORKDAY(D$48,MID(G24,2,3),Feuil1!D$2:D$14)) -> 46168 | F24: Soir | G24: J-3
A25: Délai pour la clôture des taches GT,GX et GS | E25: =IF(G25="J",D25,WORKDAY(D$48,MID(G25,2,3),Feuil1!D$2:D$14)) -> 46168 | F25: Soir | G25: J-3
A26: Arrêté ventes exploitation | E26: =IF(G26="J",D26,WORKDAY(D$48,MID(G26,2,3),Feuil1!D$2:D$14)) -> 46168 | F26: Soir | G26: J-3
A27: Arrêté de saisie des factures Open Portal Campus | E27: =IF(G27="J",D27,WORKDAY(D$48,MID(G27,2,3),Feuil1!D$2:D$14)) -> 46168 | F27: Soir | G27: J-3
B28: Calcul des PAR CID | E28: =IF(G28="J",D28,WORKDAY(D$48,MID(G28,2,3),Feuil1!D$2:D$14)) -> 46168 | F28: Soir | G28: J-3
A29: Arrêté de saisie des factures energies | E29: =IF(G29="J",D29,WORKDAY(D$48,MID(G29,2,3),Feuil1!D$2:D$14)) -> 46168 | F29: Soir | G29: J-3
B30: Refacturation intra-groupe premier traitement | E30: =IF(G30="J",D30,WORKDAY(D$48,MID(G30,2,3),Feuil1!D$2:D$14)) -> 46168 | F30: Nuit | G30: J-3
B31: Dernier passage des abonnements GL dans Oracle | E31: =IF(G31="J",D31,WORKDAY(D$48,MID(G31,2,3),Feuil1!D$2:D$14)) -> 46168 | F31: Nuit | G31: J-3
B32: Incorporation des écritures de M.O. | E32: =IF(G32="J",D32,WORKDAY(D$48,MID(G32,2,3),Feuil1!D$2:D$14)) -> 46168 | F32: Nuit | G32: J-3
B33: Traitement PIRENE (calcul des CAP, valorisation des stocks, ventes) | E33: =IF(G33="J",D33,WORKDAY(D$48,MID(G33,2,3),Feuil1!D$2:D$14)) -> 46168 | F33: Nuit | G33: J-3
B34: Calcul des CAP Gaz, Chaleur et électricité CELERIS | E34: =IF(G34="J",D34,WORKDAY(D$48,MID(G34,2,3),Feuil1!D$2:D$14)) -> 46168 | F34: Nuit | G34: J-3
C35: Mise à disposition des états de REFAC au format PDF sur le drive pour les régions | E35: =IF(G35="J",D35,WORKDAY(D$48,MID(G35,2,3),Feuil1!D$2:D$14)) -> 46169 | F35: Matin | G35: J-2
A36: Modification manuelle des PAR Exploitation mensuels CID et CAP Céleris | E36: =IF(G36="J",D36,WORKDAY(D$48,MID(G36,2,3),Feuil1!D$2:D$14)) -> 46169 | F36: Journée | G36: J-2
B37: Génération des écritures des PAR Exploitation mensuels CID | E37: =IF(G37="J",D37,WORKDAY(D$48,MID(G37,2,3),Feuil1!D$2:D$14)) -> 46169 | F37: 17H | G37: J-2
B38: Génération des écritures de CAP CELERIS | E38: =IF(G38="J",D38,WORKDAY(D$48,MID(G38,2,3),Feuil1!D$2:D$14)) -> 46169 | F38: 17H | G38: J-2
B39: Incorporation des écritures de PAR Exploitation mensuels CID | E39: =IF(G39="J",D39,WORKDAY(D$48,MID(G39,2,3),Feuil1!D$2:D$14)) -> 46169 | F39: Nuit | G39: J-2
B40: Incorporation des écritures PIRENE (calcul des CAP, valorisation des stocks, ventes) | E40: =IF(G40="J",D40,WORKDAY(D$48,MID(G40,2,3),Feuil1!D$2:D$14)) -> 46169 | F40: Nuit | G40: J-2
B41: Incorporation des écritures de CAP Gaz, Chaleur et électricité CELERIS | E41: =IF(G41="J",D41,WORKDAY(D$48,MID(G41,2,3),Feuil1!D$2:D$14)) -> 46169 | F41: Nuit | G41: J-2
B42: Refacturation intra-groupe Deuxième traitement | E42: =IF(G42="J",D42,WORKDAY(D$48,MID(G42,2,3),Feuil1!D$2:D$14)) -> 46169 | F42: Nuit | G42: J-2
C43: Mise disposition du fichier Harry Energy | E43: =IF(G43="J",D43,WORKDAY(D$48,MID(G43,2,3),Feuil1!D$2:D$14)) -> 46169 | F43: Nuit | G43: J-2
C44: Mise à disposition des états de REFAC au format PDF sur le drive pour les régions | E44: =IF(G44="J",D44,WORKDAY(D$48,MID(G44,2,3),Feuil1!D$2:D$14)) -> 46170 | F44: Matin | G44: J-1
B45: Fermeture automatique des commandes liées aux factures intra groupe CITY du mois | E45: =IF(G45="J",D45,WORKDAY(D$48,MID(G45,2,3),Feuil1!D$2:D$14)) -> 46170 | F45: Matin | G45: J-1
B46: Refacturation intra-groupe Troisième traitement | E46: =IF(G46="J",D46,WORKDAY(D$48,MID(G46,2,3),Feuil1!D$2:D$14)) -> 46170 | F46: Nuit | G46: J-1
C47: Mise à disposition des états de REFAC au format PDF sur le drive pour les régions | D47: 46171 | E47: =IF(G47="J",D47,WORKDAY(D$48,MID(G47,2,3),Feuil1!D$2:D$14)) -> 46171 | F47: Matin | G47: J
A48: FERMETURE DE L'APPLICATION - CLOTURE PROVISOIRE GL - DEFINITIVES : AP - AR - PO | D48: 46171 | E48: =IF(G48="J",D48,WORKDAY(D$48,MID(G48,2,3),Feuil1!D$2:D$14)) -> 46171 | F48: Nuit | G48: J
B49: Refacturation intra-groupe (dernier passage) | D49: 46171 | E49: =IF(G49="J",D49,WORKDAY(D$48,MID(G49,2,3),Feuil1!D$2:D$14)) -> 46171 | F49: Nuit | G49: J
B50: Calcul des CAP fournisseurs et incorporation des écritures | D50: 46171 | E50: =IF(G50="J",D50,WORKDAY(D$48,MID(G50,2,3),Feuil1!D$2:D$14)) -> 46171 | F50: Nuit | G50: J
B51: Calcul des CAP spécifiques aux contrats de sous traitance et incorporation des écritures | D51: 46171 | E51: =IF(G51="J",D51,WORKDAY(D$48,MID(G51,2,3),Feuil1!D$2:D$14)) -> 46171 | F51: Nuit | G51: J
B52: Calcul et écriture des TEC et PCA (codes R) travaux en cours - produits constatés d'avance | D52: 46171 | E52: =IF(G52="J",D52,WORKDAY(D$48,MID(G52,2,3),Feuil1!D$2:D$14)) -> 46171 | F52: Nuit | G52: J
B53: Calcul et écriture des charges d'avance sur sinistres | D53: 46171 | E53: =IF(G53="J",D53,WORKDAY(D$48,MID(G53,2,3),Feuil1!D$2:D$14)) -> 46171 | F53: Nuit | G53: J
B54: Equilibrage comptable par centre de gestion | D54: 46171 | E54: =IF(G54="J",D54,WORKDAY(D$48,MID(G54,2,3),Feuil1!D$2:D$14)) -> 46171 | F54: Nuit | G54: J
C55: Mise à disposition des états de REFAC au format PDF sur le drive pour les régions | E55: =IF(G55="J",D55,WORKDAY(D$48,MID(G55,2,3),Feuil1!D$2:D$14)) -> 46174 | F55: Matin | G55: J+1
C56: Mise à disposition des états de TVA (AP, AR) sur le drive pour les régions | E56: =IF(G56="J",D56,WORKDAY(D$48,MID(G56,2,3),Feuil1!D$2:D$14)) -> 46174 | F56: Matin | G56: J+1
C57: Mise à disposition des états CAP PO et CAP SSTR sur le drive pour les régions | E57: =IF(G57="J",D57,WORKDAY(D$48,MID(G57,2,3),Feuil1!D$2:D$14)) -> 46174 | F57: Matin | G57: J+1
B58: Imputation (posting) des écritures GL saisies dans la matinée | E58: =IF(G58="J",D58,WORKDAY(D$48,MID(G58,2,3),Feuil1!D$2:D$14)) -> 46174 | F58: 13H | G58: J+1
B59: Extourne des écritures de TEC et PCA travaux en cours - produits constatés d'avance | E59: =IF(G59="J",D59,WORKDAY(D$48,MID(G59,2,3),Feuil1!D$2:D$14)) -> 46174 | F59: Nuit | G59: J+1
B60: Extourne des écritures de charges d'avance sur sinistres | E60: =IF(G60="J",D60,WORKDAY(D$48,MID(G60,2,3),Feuil1!D$2:D$14)) -> 46174 | F60: Nuit | G60: J+1
B61: Imputation (posting) des écritures GL saisies dans la matinée | E61: =IF(G61="J",D61,WORKDAY(D$48,MID(G61,2,3),Feuil1!D$2:D$14)) -> 46175 | F61: 13H | G61: J+2
A62: CLOTURE DEFINITIVE DE GL | E62: =IF(G62="J",D62,WORKDAY(D$48,MID(G62,2,3),Feuil1!D$2:D$14)) -> 46175 | F62: 19H | G62: J+2
B63: Equilibrage comptable par centre de gestion | E63: =IF(G63="J",D63,WORKDAY(D$48,MID(G63,2,3),Feuil1!D$2:D$14)) -> 46176 | F63: Nuit | G63: J+3
B64: Alimentation de la Garantie Totale | E64: =IF(G64="J",D64,WORKDAY(D$48,MID(G64,2,3),Feuil1!D$2:D$14)) -> 46176 | F64: Nuit | G64: J+3
C65: Mise à disposition des états de TVA (GL) sur le drive pour les régions | E65: =IF(G65="J",D65,WORKDAY(D$48,MID(G65,2,3),Feuil1!D$2:D$14)) -> 46176 | F65: Matin | G65: J+3
C66: Mise à disposition des flux et soldes | E66: =IF(G66="J",D66,WORKDAY(D$48,MID(G66,2,3),Feuil1!D$2:D$14)) -> 46176 | F66: Matin | G66: J+3
C67: Mise à disposition de l'état de contrôle des retraitements IFRS | E67: =IF(G67="J",D67,WORKDAY(D$48,MID(G67,2,3),Feuil1!D$2:D$14)) -> 46176 | F67: Matin | G67: J+3
C68: Mise à disposition du fichier d'alimentation de Magnitude sur le drive pour les régions | E68: =IF(G68="J",D68,WORKDAY(D$48,MID(G68,2,3),Feuil1!D$2:D$14)) -> 46176 | F68: Matin | G68: J+3
B69: Incorporation des écritures à contrepassation sur mois suivant (2ème vendredi de chaque mois) | E69: 46185 | F69: Nuit
C70: Mise à disposition des échéanciers provisoires GROUPE sur vos clés régions | E70: =IF(G70="J",D70,WORKDAY(D$48,MID(G70,2,3),Feuil1!D$2:D$14)) -> 46185 | F70: Matin | G70: J+10
A71: Validation de l'échéancier GROUPE + Envoi des ordres de virements à CDPG + Envoi des avis de virements par mail aux Frs | E71: =IF(G71="J",D71,WORKDAY(D$48,MID(G71,2,3),Feuil1!D$2:D$14)) -> 46185 | F71: Soir | G71: J+10
B72: PO Fermeture automatique des commandes (15 du mois) | E72: 46188 | F72: Nuit
C73: Mise à disposition des commandes fermées dans le drive pour les régions | E73: 46193 | F73: Matin
C74: Envoi du mail de confirmation des virements fournisseurs GROUPE | E74: =IF(G74="J",D74,WORKDAY(D$48,MID(G74,2,3),Feuil1!D$2:D$14)) -> 46188 | F74: Matin | G74: J+11
B75: Incorporation des encaissements suite à échéancier Groupe | E75: =IF(G75="J",D75,WORKDAY(D$48,MID(G75,2,3),Feuil1!D$2:D$14)) -> 46188 | F75: Nuit | G75: J+11

Sheet JUIN 2026
A1: CALENDRIER CLOTURE JUIN 2026
A2: ARRETE | B2: TRAITEMENT | C2: RESTITUTION | D2: Date de Référence J
A3: Date limite de remontée des PV pour mise en service des investissements | E3: =IF(G3="J",D3,WORKDAY(D$48,MID(G3,2,3),Feuil1!D$2:D$14)) -> 46191 | F3: Matin | G3: J-8
A4: Premiers relevés de compteurs et de stocks | E4: =IF(G4="J",D4,WORKDAY(D$48,MID(G4,2,3),Feuil1!D$2:D$14)) -> 46192 | F4: Matin | G4: J-7
B5: Incorporation en comptabilité des écritures GL de paie | E5: =IF(G5="J",D5,WORKDAY(D$48,MID(G5,2,3),Feuil1!D$2:D$14)) -> 46196 | F5: Nuit | G5: J-5
C6: Campagne Fournisseurs TIERS FDM - Mise à disposition des échéanciers provisoires | E6: =IF(G6="J",D6,WORKDAY(D$48,MID(G6,2,3),Feuil1!D$2:D$14)) -> 46196 | F6: Matin | G6: J-5
A7: ARCAS | B7: Envoi à la compta Siège du fichier PROGEFI par le service Trésorerie incluant les remarques des Uos | E7: =IF(G7="J",D7,WORKDAY(D$48,MID(G7,2,3),Feuil1!D$2:D$14)) -> 46196 | F7: Matin | G7: J-5
A8: Fermeture du livre comptable FA | E8: =IF(G8="J",D8,WORKDAY(D$48,MID(G8,2,3),Feuil1!D$2:D$14)) -> 46196 | F8: Soir | G8: J-5
B9: Premier passage des abonnements GL dans Oracle | E9: =IF(G9="J",D9,WORKDAY(D$48,MID(G9,2,3),Feuil1!D$2:D$14)) -> 46196 | F9: Nuit | G9: J-5
B10: Incorporation des écritures d'amortissements | E10: =IF(G10="J",D10,WORKDAY(D$48,MID(G10,2,3),Feuil1!D$2:D$14)) -> 46196 | F10: Nuit | G10: J-5
B11: Incorporation en comptabilité des écritures GL et provisions DACAR | E11: =IF(G11="J",D11,WORKDAY(D$48,MID(G11,2,3),Feuil1!D$2:D$14)) -> 46196 | F11: Nuit | G11: J-5
A12: Campagne Fournisseurs TIERS FDM - Mise à disposition des pupitres et envoi du mail de Projection | E12: =IF(G12="J",D12,WORKDAY(D$48,MID(G12,2,3),Feuil1!D$2:D$14)) -> 46197 | F12: Matin | G12: J-4
A13: Date limite d'intégration des factures de carburant et péages (DACAR) | E13: =IF(G13="J",D13,WORKDAY(D$48,MID(G13,2,3),Feuil1!D$2:D$14)) -> 46197 | F13: Journée | G13: J-4
A14: CALLISTO | B14: Derniers retours des Uos (mise à jour navettes : subventions, exceptions) et remarques sur traitement M-1 | E14: =IF(G14="J",D14,WORKDAY(D$48,MID(G14,2,3),Feuil1!D$2:D$14)) -> 46197 | F14: Soir | G14: J-4
A15: ARCAS | B15: Traitement ARCAS pour incorporation des écritures d'abonnement | E15: =IF(G15="J",D15,WORKDAY(D$48,MID(G15,2,3),Feuil1!D$2:D$14)) -> 46197 | F15: Soir | G15: J-4
A16: Dernières transmissions des heures de M.O. | E16: =IF(G16="J",D16,WORKDAY(D$48,MID(G16,2,3),Feuil1!D$2:D$14)) -> 46197 | F16: Soir | G16: J-4
A17: Dernières saisies et validation des relevés de compteur et de stocks et des livraisons | E17: =IF(G17="J",D17,WORKDAY(D$48,MID(G17,2,3),Feuil1!D$2:D$14)) -> 46197 | F17: Soir | G17: J-4
A18: Validation de l'échéancier TIERS FDM + Envoi des ordres de virements à CDPG + Envoi des avis de virements par mail aux Frs | E18: =IF(G18="J",D18,WORKDAY(D$48,MID(G18,2,3),Feuil1!D$2:D$14)) -> 46197 | F18: Soir | G18: J-4
B19: Second passage des abonnements GL dans Oracle | E19: =IF(G19="J",D19,WORKDAY(D$48,MID(G19,2,3),Feuil1!D$2:D$14)) -> 46197 | F19: Nuit | G19: J-4
B20: Calcul de la M.O. au THO (VACHE) | E20: =IF(G20="J",D20,WORKDAY(D$48,MID(G20,2,3),Feuil1!D$2:D$14)) -> 46197 | F20: Nuit | G20: J-4
C21: Envoi du mail de confirmation des virements TIERS FDM | E21: =IF(G21="J",D21,WORKDAY(D$48,MID(G21,2,3),Feuil1!D$2:D$14)) -> 46198 | F21: Matin | G21: J-3
A22: CALLISTO | B22: Traitement CALLISTO et incorporation des écritures IFRS + envoi fichiers justificatifs aux Uos | E22: =IF(G22="J",D22,WORKDAY(D$48,MID(G22,2,3),Feuil1!D$2:D$14)) -> 46198 | F22: Soir | G22: J-3
A23: ARCAS | B23: Traitement ARCAS et incorporation des écritures IFRS + envoi fichiers justificatifs aux Uos | E23: =IF(G23="J",D23,WORKDAY(D$48,MID(G23,2,3),Feuil1!D$2:D$14)) -> 46198 | F23: Soir | G23: J-3
A24: Arrêté ventes travaux (CITY) | E24: =IF(G24="J",D24,WORKDAY(D$48,MID(G24,2,3),Feuil1!D$2:D$14)) -> 46198 | F24: Soir | G24: J-3
A25: Délai pour la clôture des taches GT,GX et GS | E25: =IF(G25="J",D25,WORKDAY(D$48,MID(G25,2,3),Feuil1!D$2:D$14)) -> 46198 | F25: Soir | G25: J-3
A26: Arrêté ventes exploitation | E26: =IF(G26="J",D26,WORKDAY(D$48,MID(G26,2,3),Feuil1!D$2:D$14)) -> 46198 | F26: Soir | G26: J-3
A27: Arrêté de saisie des factures Open Portal Campus | E27: =IF(G27="J",D27,WORKDAY(D$48,MID(G27,2,3),Feuil1!D$2:D$14)) -> 46198 | F27: Soir | G27: J-3
B28: Calcul des PAR CID | E28: =IF(G28="J",D28,WORKDAY(D$48,MID(G28,2,3),Feuil1!D$2:D$14)) -> 46198 | F28: Soir | G28: J-3
A29: Arrêté de saisie des factures energies | E29: =IF(G29="J",D29,WORKDAY(D$48,MID(G29,2,3),Feuil1!D$2:D$14)) -> 46198 | F29: Soir | G29: J-3
B30: Refacturation intra-groupe premier traitement | E30: =IF(G30="J",D30,WORKDAY(D$48,MID(G30,2,3),Feuil1!D$2:D$14)) -> 46198 | F30: Nuit | G30: J-3
B31: Dernier passage des abonnements GL dans Oracle | E31: =IF(G31="J",D31,WORKDAY(D$48,MID(G31,2,3),Feuil1!D$2:D$14)) -> 46198 | F31: Nuit | G31: J-3
B32: Incorporation des écritures de M.O. | E32: =IF(G32="J",D32,WORKDAY(D$48,MID(G32,2,3),Feuil1!D$2:D$14)) -> 46198 | F32: Nuit | G32: J-3
B33: Traitement PIRENE (calcul des CAP, valorisation des stocks, ventes) | E33: =IF(G33="J",D33,WORKDAY(D$48,MID(G33,2,3),Feuil1!D$2:D$14)) -> 46198 | F33: Nuit | G33: J-3
B34: Calcul des CAP Gaz, Chaleur et électricité CELERIS | E34: =IF(G34="J",D34,WORKDAY(D$48,MID(G34,2,3),Feuil1!D$2:D$14)) -> 46198 | F34: Nuit | G34: J-3
C35: Mise à disposition des états de REFAC au format PDF sur le drive pour les régions | E35: =IF(G35="J",D35,WORKDAY(D$48,MID(G35,2,3),Feuil1!D$2:D$14)) -> 46199 | F35: Matin | G35: J-2
A36: Modification manuelle des PAR Exploitation mensuels CID et CAP Céleris | E36: =IF(G36="J",D36,WORKDAY(D$48,MID(G36,2,3),Feuil1!D$2:D$14)) -> 46199 | F36: Journée | G36: J-2
B37: Génération des écritures des PAR Exploitation mensuels CID | E37: =IF(G37="J",D37,WORKDAY(D$48,MID(G37,2,3),Feuil1!D$2:D$14)) -> 46199 | F37: 17H | G37: J-2
B38: Génération des écritures de CAP CELERIS | E38: =IF(G38="J",D38,WORKDAY(D$48,MID(G38,2,3),Feuil1!D$2:D$14)) -> 46199 | F38: 17H | G38: J-2
B39: Incorporation des écritures de PAR Exploitation mensuels CID | E39: =IF(G39="J",D39,WORKDAY(D$48,MID(G39,2,3),Feuil1!D$2:D$14)) -> 46199 | F39: Nuit | G39: J-2
B40: Incorporation des écritures PIRENE (calcul des CAP, valorisation des stocks, ventes) | E40: =IF(G40="J",D40,WORKDAY(D$48,MID(G40,2,3),Feuil1!D$2:D$14)) -> 46199 | F40: Nuit | G40: J-2
B41: Incorporation des écritures de CAP Gaz, Chaleur et électricité CELERIS | E41: =IF(G41="J",D41,WORKDAY(D$48,MID(G41,2,3),Feuil1!D$2:D$14)) -> 46199 | F41: Nuit | G41: J-2
B42: Refacturation intra-groupe Deuxième traitement | E42: =IF(G42="J",D42,WORKDAY(D$48,MID(G42,2,3),Feuil1!D$2:D$14)) -> 46199 | F42: Nuit | G42: J-2
C43: Mise disposition du fichier Harry Energy | E43: =IF(G43="J",D43,WORKDAY(D$48,MID(G43,2,3),Feuil1!D$2:D$14)) -> 46199 | F43: Nuit | G43: J-2
C44: Mise à disposition des états de REFAC au format PDF sur le drive pour les régions | E44: =IF(G44="J",D44,WORKDAY(D$48,MID(G44,2,3),Feuil1!D$2:D$14)) -> 46202 | F44: Matin | G44: J-1
B45: Fermeture automatique des commandes liées aux factures intra groupe CITY du mois | E45: =IF(G45="J",D45,WORKDAY(D$48,MID(G45,2,3),Feuil1!D$2:D$14)) -> 46202 | F45: Matin | G45: J-1
B46: Refacturation intra-groupe Troisième traitement | E46: =IF(G46="J",D46,WORKDAY(D$48,MID(G46,2,3),Feuil1!D$2:D$14)) -> 46202 | F46: Nuit | G46: J-1
C47: Mise à disposition des états de REFAC au format PDF sur le drive pour les régions | D47: 46203 | E47: =IF(G47="J",D47,WORKDAY(D$48,MID(G47,2,3),Feuil1!D$2:D$14)) -> 46203 | F47: Matin | G47: J
A48: FERMETURE DE L'APPLICATION - CLOTURE PROVISOIRE GL - DEFINITIVES : AP - AR - PO | D48: 46203 | E48: =IF(G48="J",D48,WORKDAY(D$48,MID(G48,2,3),Feuil1!D$2:D$14)) -> 46203 | F48: Nuit | G48: J
B49: Refacturation intra-groupe (dernier passage) | D49: 46203 | E49: =IF(G49="J",D49,WORKDAY(D$48,MID(G49,2,3),Feuil1!D$2:D$14)) -> 46203 | F49: Nuit | G49: J
B50: Calcul des CAP fournisseurs et incorporation des écritures | D50: 46203 | E50: =IF(G50="J",D50,WORKDAY(D$48,MID(G50,2,3),Feuil1!D$2:D$14)) -> 46203 | F50: Nuit | G50: J
B51: Calcul des CAP spécifiques aux contrats de sous traitance et incorporation des écritures | D51: 46203 | E51: =IF(G51="J",D51,WORKDAY(D$48,MID(G51,2,3),Feuil1!D$2:D$14)) -> 46203 | F51: Nuit | G51: J
B52: Calcul et écriture des TEC et PCA (codes R) travaux en cours - produits constatés d'avance | D52: 46203 | E52: =IF(G52="J",D52,WORKDAY(D$48,MID(G52,2,3),Feuil1!D$2:D$14)) -> 46203 | F52: Nuit | G52: J
B53: Calcul et écriture des charges d'avance sur sinistres | D53: 46203 | E53: =IF(G53="J",D53,WORKDAY(D$48,MID(G53,2,3),Feuil1!D$2:D$14)) -> 46203 | F53: Nuit | G53: J
B54: Equilibrage comptable par centre de gestion | D54: 46203 | E54: =IF(G54="J",D54,WORKDAY(D$48,MID(G54,2,3),Feuil1!D$2:D$14)) -> 46203 | F54: Nuit | G54: J
C55: Mise à disposition des états de REFAC au format PDF sur le drive pour les régions | E55: =IF(G55="J",D55,WORKDAY(D$48,MID(G55,2,3),Feuil1!D$2:D$14)) -> 46204 | F55: Matin | G55: J+1
C56: Mise à disposition des états de TVA (AP, AR) sur le drive pour les régions | E56: =IF(G56="J",D56,WORKDAY(D$48,MID(G56,2,3),Feuil1!D$2:D$14)) -> 46204 | F56: Matin | G56: J+1
C57: Mise à disposition des états CAP PO et CAP SSTR sur le drive pour les régions | E57: =IF(G57="J",D57,WORKDAY(D$48,MID(G57,2,3),Feuil1!D$2:D$14)) -> 46204 | F57: Matin | G57: J+1
B58: Imputation (posting) des écritures GL saisies dans la matinée | E58: =IF(G58="J",D58,WORKDAY(D$48,MID(G58,2,3),Feuil1!D$2:D$14)) -> 46204 | F58: 13H | G58: J+1
B59: Extourne des écritures de TEC et PCA travaux en cours - produits constatés d'avance | E59: =IF(G59="J",D59,WORKDAY(D$48,MID(G59,2,3),Feuil1!D$2:D$14)) -> 46204 | F59: Nuit | G59: J+1
B60: Extourne des écritures de charges d'avance sur sinistres | E60: =IF(G60="J",D60,WORKDAY(D$48,MID(G60,2,3),Feuil1!D$2:D$14)) -> 46204 | F60: Nuit | G60: J+1
B61: Imputation (posting) des écritures GL saisies dans la matinée | E61: =IF(G61="J",D61,WORKDAY(D$48,MID(G61,2,3),Feuil1!D$2:D$14)) -> 46205 | F61: 13H | G61: J+2
A62: CLOTURE DEFINITIVE DE GL | E62: =IF(G62="J",D62,WORKDAY(D$48,MID(G62,2,3),Feuil1!D$2:D$14)) -> 46205 | F62: 19H | G62: J+2
B63: Equilibrage comptable par centre de gestion | E63: =IF(G63="J",D63,WORKDAY(D$48,MID(G63,2,3),Feuil1!D$2:D$14)) -> 46206 | F63: Nuit | G63: J+3
B64: Alimentation de la Garantie Totale | E64: =IF(G64="J",D64,WORKDAY(D$48,MID(G64,2,3),Feuil1!D$2:D$14)) -> 46206 | F64: Nuit | G64: J+3
C65: Mise à disposition des états de TVA (GL) sur le drive pour les régions | E65: =IF(G65="J",D65,WORKDAY(D$48,MID(G65,2,3),Feuil1!D$2:D$14)) -> 46206 | F65: Matin | G65: J+3
C66: Mise à disposition des flux et soldes | E66: =IF(G66="J",D66,WORKDAY(D$48,MID(G66,2,3),Feuil1!D$2:D$14)) -> 46206 | F66: Matin | G66: J+3
C67: Mise à disposition de l'état de contrôle des retraitements IFRS | E67: =IF(G67="J",D67,WORKDAY(D$48,MID(G67,2,3),Feuil1!D$2:D$14)) -> 46206 | F67: Matin | G67: J+3
C68: Mise à disposition du fichier d'alimentation de Magnitude sur le drive pour les régions | E68: =IF(G68="J",D68,WORKDAY(D$48,MID(G68,2,3),Feuil1!D$2:D$14)) -> 46206 | F68: Matin | G68: J+3
C69: Mise à disposition des Balances Clients et Fournisseurs au 30/06 sur le drive pour les régions | E69: =IF(G69="J",D69,WORKDAY(D$48,MID(G69,2,3),Feuil1!D$2:D$14)) -> 46209 | F69: Matin | G69: J+4
B70: Traitement de Surtaxe Communale | E70: =IF(G70="J",D70,WORKDAY(D$48,MID(G70,2,3),Feuil1!D$2:D$14)) -> 46211 | F70: Nuit | G70: J+6
C71: Mise à disposition des états de surtaxe communale sur le drive pour les régions | E71: =IF(G71="J",D71,WORKDAY(D$48,MID(G71,2,3),Feuil1!D$2:D$14)) -> 46212 | F71: Matin | G71: J+7
B72: Incorporation des écritures à contrepassation sur mois suivant (2ème vendredi de chaque mois) | E72: 46213 | F72: Nuit
C73: Mise à disposition des échéanciers provisoires GROUPE sur vos clés régions | E73: =IF(G73="J",D73,WORKDAY(D$48,MID(G73,2,3),Feuil1!D$2:D$14)) -> 46218 | F73: Matin | G73: J+10
A74: Validation de l'échéancier GROUPE + Envoi des ordres de virements à CDPG + Envoi des avis de virements par mail aux Frs | E74: =IF(G74="J",D74,WORKDAY(D$48,MID(G74,2,3),Feuil1!D$2:D$14)) -> 46218 | F74: Soir | G74: J+10
B75: PO Fermeture automatique des commandes (15 du mois) | E75: 46218 | F75: Nuit
C76: Mise à disposition des commandes fermées dans le drive pour les régions | E76: 46223 | F76: Matin
C77: Envoi du mail de confirmation des virements fournisseurs GROUPE | E77: =IF(G77="J",D77,WORKDAY(D$48,MID(G77,2,3),Feuil1!D$2:D$14)) -> 46219 | F77: Matin | G77: J+11
B78: Incorporation des encaissements suite à échéancier Groupe | E78: =IF(G78="J",D78,WORKDAY(D$48,MID(G78,2,3),Feuil1!D$2:D$14)) -> 46219 | F78: Nuit | G78: J+11
