Workbook

Sheet Feuil1
A1: Année | B1: 2026 | D1: Jour férie | E1: Valeur retour
D2: =DATE($B$1,1,1) -> 46023 | E2: Oui
D3: =FLOOR(DAY(MINUTE($B$1/38)/2+56)&"/5/"&$B$1,7)-34 -> 46117 | E3: Oui
D4: =D3 + 1 -> 46118 | E4: Oui
D5: =DATE($B$1,5,1) -> 46143 | E5: Oui
D6: =DATE($B$1,5,8) -> 46150 | E6: Oui
D7: =D3+"39" -> 46156 | E7: Oui
D8: =D3 + 49 -> 46166 | E8: Oui
D9: =D3 + 50 -> 46167 | E9: Oui
D10: =DATE($B$1,7,14) -> 46217 | E10: Oui
D11: =DATE($B$1,8,15) -> 46249 | E11: Oui
D12: =DATE($B$1,11,1) -> 46327 | E12: Oui
D13: =DATE($B$1,11,11) -> 46337 | E13: Oui
D14: =DATE($B$1,12,25) -> 46381 | E14: Oui
D15: 46023 | E15: Oui

Sheet AOUT 2026
A1: CALENDRIER CLOTURE AOUT 2026
A2: ARRETE | B2: TRAITEMENT | C2: RESTITUTION | D2: Date de Référence J
A3: Date limite de remontée des PV pour mise en service des investissements | E3: =IF(G3="J",D3,WORKDAY(D$53,MID(G3,2,3),Feuil1!D$2:D$14)) -> 46253 | F3: Matin | G3: J-8
A4: Campagne Fournisseurs Virements Tiers Express | E4: =IF(G4="J",D4,WORKDAY(D$53,MID(G4,2,3),Feuil1!D$2:D$14)) -> 46253 | F4: Nuit | G4: J-8
A5: Premiers relevés de compteurs et de stocks | E5: =IF(G5="J",D5,WORKDAY(D$53,MID(G5,2,3),Feuil1!D$2:D$14)) -> 46254 | F5: Matin | G5: J-7
A6: Campagne Fournisseurs Virements Tiers Express | E6: =IF(G6="J",D6,WORKDAY(D$53,MID(G6,2,3),Feuil1!D$2:D$14)) -> 46254 | F6: Nuit | G6: J-7
B7: Incorporation en comptabilité des écritures GL de paie | E7: =IF(G7="J",D7,WORKDAY(D$53,MID(G7,2,3),Feuil1!D$2:D$14)) -> 46255 | F7: Nuit | G7: J-6
A8: Campagne Fournisseurs Virements Tiers Express | E8: =IF(G8="J",D8,WORKDAY(D$53,MID(G8,2,3),Feuil1!D$2:D$14)) -> 46255 | F8: Nuit | G8: J-6
A9: ARCAS | B9: Envoi à la compta Siège du fichier PROGEFI par le service Trésorerie incluant les remarques des Uos | E9: =IF(G9="J",D9,WORKDAY(D$53,MID(G9,2,3),Feuil1!D$2:D$14)) -> 46258 | F9: Matin | G9: J-5
A10: Fermeture du livre comptable FA | E10: =IF(G10="J",D10,WORKDAY(D$53,MID(G10,2,3),Feuil1!D$2:D$14)) -> 46258 | F10: Soir | G10: J-5
B11: Premier passage des abonnements GL dans Oracle | E11: =IF(G11="J",D11,WORKDAY(D$53,MID(G11,2,3),Feuil1!D$2:D$14)) -> 46258 | F11: Nuit | G11: J-5
B12: Incorporation des écritures d'amortissements | E12: =IF(G12="J",D12,WORKDAY(D$53,MID(G12,2,3),Feuil1!D$2:D$14)) -> 46258 | F12: Nuit | G12: J-5
B13: Incorporation en comptabilité des écritures GL et provisions DACAR | E13: =IF(G13="J",D13,WORKDAY(D$53,MID(G13,2,3),Feuil1!D$2:D$14)) -> 46258 | F13: Nuit | G13: J-5
A14: Campagne Fournisseurs Virements NDF Employé | E14: =IF(G14="J",D14,WORKDAY(D$53,MID(G14,2,3),Feuil1!D$2:D$14)) -> 46258 | F14: Nuit | G14: J-5
A15: Campagne Fournisseurs Virements Tiers Express | E15: =IF(G15="J",D15,WORKDAY(D$53,MID(G15,2,3),Feuil1!D$2:D$14)) -> 46258 | F15: Nuit | G15: J-5
A16: Date limite d'intégration des factures de carburant et péages (DACAR) | E16: =IF(G16="J",D16,WORKDAY(D$53,MID(G16,2,3),Feuil1!D$2:D$14)) -> 46259 | F16: Journée | G16: J-4
A17: CALLISTO | B17: Derniers retours des Uos (mise à jour navettes : subventions, exceptions) et remarques sur traitement M-1 | E17: =IF(G17="J",D17,WORKDAY(D$53,MID(G17,2,3),Feuil1!D$2:D$14)) -> 46259 | F17: Soir | G17: J-4
A18: ARCAS | B18: Traitement ARCAS pour incorporation des écritures d'abonnement | E18: =IF(G18="J",D18,WORKDAY(D$53,MID(G18,2,3),Feuil1!D$2:D$14)) -> 46259 | F18: Soir | G18: J-4
A19: Dernières transmissions des heures de M.O. | E19: =IF(G19="J",D19,WORKDAY(D$53,MID(G19,2,3),Feuil1!D$2:D$14)) -> 46259 | F19: Soir | G19: J-4
A20: Dernières saisies et validation des relevés de compteur et de stocks et des livraisons | E20: =IF(G20="J",D20,WORKDAY(D$53,MID(G20,2,3),Feuil1!D$2:D$14)) -> 46259 | F20: Soir | G20: J-4
A21: Campagne Fournisseurs Virements Tiers Express | E21: =IF(G21="J",D21,WORKDAY(D$53,MID(G21,2,3),Feuil1!D$2:D$14)) -> 46259 | F21: Nuit | G21: J-4
B22: Second passage des abonnements GL dans Oracle | E22: =IF(G22="J",D22,WORKDAY(D$53,MID(G22,2,3),Feuil1!D$2:D$14)) -> 46259 | F22: Nuit | G22: J-4
B23: Calcul de la M.O. au THO (VACHE) | E23: =IF(G23="J",D23,WORKDAY(D$53,MID(G23,2,3),Feuil1!D$2:D$14)) -> 46259 | F23: Nuit | G23: J-4
A24: CALLISTO | B24: Traitement CALLISTO et incorporation des écritures IFRS + envoi fichiers justificatifs aux Uos | E24: =IF(G24="J",D24,WORKDAY(D$53,MID(G24,2,3),Feuil1!D$2:D$14)) -> 46260 | F24: Soir | G24: J-3
A25: ARCAS | B25: Traitement ARCAS et incorporation des écritures IFRS + envoi fichiers justificatifs aux Uos | E25: =IF(G25="J",D25,WORKDAY(D$53,MID(G25,2,3),Feuil1!D$2:D$14)) -> 46260 | F25: Soir | G25: J-3
A26: Arrêté ventes travaux (CITY) | E26: =IF(G26="J",D26,WORKDAY(D$53,MID(G26,2,3),Feuil1!D$2:D$14)) -> 46260 | F26: Soir | G26: J-3
A27: Délai pour la clôture des taches GT,GX et GS | E27: =IF(G27="J",D27,WORKDAY(D$53,MID(G27,2,3),Feuil1!D$2:D$14)) -> 46260 | F27: Soir | G27: J-3
A28: Arrêté ventes exploitation | E28: =IF(G28="J",D28,WORKDAY(D$53,MID(G28,2,3),Feuil1!D$2:D$14)) -> 46260 | F28: Soir | G28: J-3
A29: Arrêté de saisie des factures Open Portal Campus | E29: =IF(G29="J",D29,WORKDAY(D$53,MID(G29,2,3),Feuil1!D$2:D$14)) -> 46260 | F29: Soir | G29: J-3
B30: Calcul des PAR CID | E30: =IF(G30="J",D30,WORKDAY(D$53,MID(G30,2,3),Feuil1!D$2:D$14)) -> 46260 | F30: Soir | G30: J-3
A31: Arrêté de saisie des factures energies | E31: =IF(G31="J",D31,WORKDAY(D$53,MID(G31,2,3),Feuil1!D$2:D$14)) -> 46260 | F31: Soir | G31: J-3
A32: Campagne Fournisseurs Virements Tiers Express | E32: =IF(G32="J",D32,WORKDAY(D$53,MID(G32,2,3),Feuil1!D$2:D$14)) -> 46260 | F32: Nuit | G32: J-3
B33: Refacturation intra-groupe premier traitement | E33: =IF(G33="J",D33,WORKDAY(D$53,MID(G33,2,3),Feuil1!D$2:D$14)) -> 46260 | F33: Nuit | G33: J-3
B34: Dernier passage des abonnements GL dans Oracle | E34: =IF(G34="J",D34,WORKDAY(D$53,MID(G34,2,3),Feuil1!D$2:D$14)) -> 46260 | F34: Nuit | G34: J-3
B35: Incorporation des écritures de M.O. | E35: =IF(G35="J",D35,WORKDAY(D$53,MID(G35,2,3),Feuil1!D$2:D$14)) -> 46260 | F35: Nuit | G35: J-3
B36: Traitement PIRENE (calcul des CAP, valorisation des stocks, ventes) | E36: =IF(G36="J",D36,WORKDAY(D$53,MID(G36,2,3),Feuil1!D$2:D$14)) -> 46260 | F36: Nuit | G36: J-3
B37: Calcul des CAP Gaz, Chaleur et électricité CELERIS | E37: =IF(G37="J",D37,WORKDAY(D$53,MID(G37,2,3),Feuil1!D$2:D$14)) -> 46260 | F37: Nuit | G37: J-3
C38: Mise à disposition des états de REFAC au format PDF sur le drive pour les régions | E38: =IF(G38="J",D38,WORKDAY(D$53,MID(G38,2,3),Feuil1!D$2:D$14)) -> 46261 | F38: Matin | G38: J-2
A39: Modification manuelle des PAR Exploitation mensuels CID et CAP Céleris | E39: =IF(G39="J",D39,WORKDAY(D$53,MID(G39,2,3),Feuil1!D$2:D$14)) -> 46261 | F39: Journée | G39: J-2
B40: Génération des écritures des PAR Exploitation mensuels CID | E40: =IF(G40="J",D40,WORKDAY(D$53,MID(G40,2,3),Feuil1!D$2:D$14)) -> 46261 | F40: 17H | G40: J-2
B41: Génération des écritures de CAP CELERIS | E41: =IF(G41="J",D41,WORKDAY(D$53,MID(G41,2,3),Feuil1!D$2:D$14)) -> 46261 | F41: 17H | G41: J-2
B42: Incorporation des écritures de PAR Exploitation mensuels CID | E42: =IF(G42="J",D42,WORKDAY(D$53,MID(G42,2,3),Feuil1!D$2:D$14)) -> 46261 | F42: Nuit | G42: J-2
B43: Incorporation des écritures PIRENE (calcul des CAP, valorisation des stocks, ventes) | E43: =IF(G43="J",D43,WORKDAY(D$53,MID(G43,2,3),Feuil1!D$2:D$14)) -> 46261 | F43: Nuit | G43: J-2
B44: Incorporation des écritures de CAP Gaz, Chaleur et électricité CELERIS | E44: =IF(G44="J",D44,WORKDAY(D$53,MID(G44,2,3),Feuil1!D$2:D$14)) -> 46261 | F44: Nuit | G44: J-2
A45: Campagne Fournisseurs Virements Tiers Express | E45: =IF(G45="J",D45,WORKDAY(D$53,MID(G45,2,3),Feuil1!D$2:D$14)) -> 46261 | F45: Nuit | G45: J-2
B46: Refacturation intra-groupe Deuxième traitement | E46: =IF(G46="J",D46,WORKDAY(D$53,MID(G46,2,3),Feuil1!D$2:D$14)) -> 46261 | F46: Nuit | G46: J-2
C47: Mise disposition du fichier Harry Energy | E47: =IF(G47="J",D47,WORKDAY(D$53,MID(G47,2,3),Feuil1!D$2:D$14)) -> 46261 | F47: Nuit | G47: J-2
C48: Mise à disposition des états de REFAC au format PDF sur le drive pour les régions | E48: =IF(G48="J",D48,WORKDAY(D$53,MID(G48,2,3),Feuil1!D$2:D$14)) -> 46262 | F48: Matin | G48: J-1
B49: Fermeture automatique des commandes liées aux factures intra groupe CITY du mois | E49: =IF(G49="J",D49,WORKDAY(D$53,MID(G49,2,3),Feuil1!D$2:D$14)) -> 46262 | F49: Matin | G49: J-1
A50: Campagne Fournisseurs Virements Tiers Express | E50: =IF(G50="J",D50,WORKDAY(D$53,MID(G50,2,3),Feuil1!D$2:D$14)) -> 46262 | F50: Nuit | G50: J-1
B51: Refacturation intra-groupe Troisième traitement | E51: =IF(G51="J",D51,WORKDAY(D$53,MID(G51,2,3),Feuil1!D$2:D$14)) -> 46262 | F51: Nuit | G51: J-1
C52: Mise à disposition des états de REFAC au format PDF sur le drive pour les régions | D52: 46265 | E52: =IF(G52="J",D52,WORKDAY(D$53,MID(G52,2,3),Feuil1!D$2:D$14)) -> 46265 | F52: Matin | G52: J
A53: FERMETURE DE L'APPLICATION - CLOTURE PROVISOIRE GL - DEFINITIVES : AP - AR - PO | D53: 46265 | E53: =IF(G53="J",D53,WORKDAY(D$53,MID(G53,2,3),Feuil1!D$2:D$14)) -> 46265 | F53: Nuit | G53: J
B54: Refacturation intra-groupe (dernier passage) | D54: 46265 | E54: =IF(G54="J",D54,WORKDAY(D$53,MID(G54,2,3),Feuil1!D$2:D$14)) -> 46265 | F54: Nuit | G54: J
B55: Calcul des CAP fournisseurs et incorporation des écritures | D55: 46265 | E55: =IF(G55="J",D55,WORKDAY(D$53,MID(G55,2,3),Feuil1!D$2:D$14)) -> 46265 | F55: Nuit | G55: J
B56: Calcul des CAP spécifiques aux contrats de sous traitance et incorporation des écritures | D56: 46265 | E56: =IF(G56="J",D56,WORKDAY(D$53,MID(G56,2,3),Feuil1!D$2:D$14)) -> 46265 | F56: Nuit | G56: J
B57: Calcul et écriture des TEC et PCA (codes R) travaux en cours - produits constatés d'avance | D57: 46265 | E57: =IF(G57="J",D57,WORKDAY(D$53,MID(G57,2,3),Feuil1!D$2:D$14)) -> 46265 | F57: Nuit | G57: J
B58: Calcul et écriture des charges d'avance sur sinistres | D58: 46265 | E58: =IF(G58="J",D58,WORKDAY(D$53,MID(G58,2,3),Feuil1!D$2:D$14)) -> 46265 | F58: Nuit | G58: J
B59: Equilibrage comptable par centre de gestion | D59: 46265 | E59: =IF(G59="J",D59,WORKDAY(D$53,MID(G59,2,3),Feuil1!D$2:D$14)) -> 46265 | F59: Nuit | G59: J
C60: Mise à disposition des états de REFAC au format PDF sur le drive pour les régions | E60: =IF(G60="J",D60,WORKDAY(D$53,MID(G60,2,3),Feuil1!D$2:D$14)) -> 46266 | F60: Matin | G60: J+1
C61: Mise à disposition des états de TVA (AP, AR) sur le drive pour les régions | E61: =IF(G61="J",D61,WORKDAY(D$53,MID(G61,2,3),Feuil1!D$2:D$14)) -> 46266 | F61: Matin | G61: J+1
C62: Mise à disposition des états CAP PO et CAP SSTR sur le drive pour les régions | E62: =IF(G62="J",D62,WORKDAY(D$53,MID(G62,2,3),Feuil1!D$2:D$14)) -> 46266 | F62: Matin | G62: J+1
B63: Imputation (posting) des écritures GL saisies dans la matinée | E63: =IF(G63="J",D63,WORKDAY(D$53,MID(G63,2,3),Feuil1!D$2:D$14)) -> 46266 | F63: 13H | G63: J+1
A64: Campagne Fournisseurs Virements NDF Employé | E64: =IF(G64="J",D64,WORKDAY(D$53,MID(G64,2,3),Feuil1!D$2:D$14)) -> 46266 | F64: Nuit | G64: J+1
A65: Campagne Fournisseurs Virements Tiers Express | E65: =IF(G65="J",D65,WORKDAY(D$53,MID(G65,2,3),Feuil1!D$2:D$14)) -> 46266 | F65: Nuit | G65: J+1
B66: Extourne des écritures de TEC et PCA travaux en cours - produits constatés d'avance | E66: =IF(G66="J",D66,WORKDAY(D$53,MID(G66,2,3),Feuil1!D$2:D$14)) -> 46266 | F66: Nuit | G66: J+1
B67: Extourne des écritures de charges d'avance sur sinistres | E67: =IF(G67="J",D67,WORKDAY(D$53,MID(G67,2,3),Feuil1!D$2:D$14)) -> 46266 | F67: Nuit | G67: J+1
B68: Imputation (posting) des écritures GL saisies dans la matinée | E68: =IF(G68="J",D68,WORKDAY(D$53,MID(G68,2,3),Feuil1!D$2:D$14)) -> 46267 | F68: 13H | G68: J+2
A69: CLOTURE DEFINITIVE DE GL | E69: =IF(G69="J",D69,WORKDAY(D$53,MID(G69,2,3),Feuil1!D$2:D$14)) -> 46267 | F69: Nuit | G69: J+2
B70: Equilibrage comptable par centre de gestion | E70: =IF(G70="J",D70,WORKDAY(D$53,MID(G70,2,3),Feuil1!D$2:D$14)) -> 46267 | F70: Nuit | G70: J+2
B71: Alimentation de la Garantie Totale | E71: =IF(G71="J",D71,WORKDAY(D$53,MID(G71,2,3),Feuil1!D$2:D$14)) -> 46267 | F71: Nuit | G71: J+2
A72: Campagne Fournisseurs Virements Tiers Express | E72: =IF(G72="J",D72,WORKDAY(D$53,MID(G72,2,3),Feuil1!D$2:D$14)) -> 46267 | F72: Nuit | G72: J+2
C73: Mise à disposition des états de TVA (GL) sur le drive pour les régions | E73: =IF(G73="J",D73,WORKDAY(D$53,MID(G73,2,3),Feuil1!D$2:D$14)) -> 46268 | F73: Matin | G73: J+3
C74: Mise à disposition des flux et soldes | E74: =IF(G74="J",D74,WORKDAY(D$53,MID(G74,2,3),Feuil1!D$2:D$14)) -> 46268 | F74: Matin | G74: J+3
C75: Mise à disposition de l'état de contrôle des retraitements IFRS | E75: =IF(G75="J",D75,WORKDAY(D$53,MID(G75,2,3),Feuil1!D$2:D$14)) -> 46268 | F75: Matin | G75: J+3
C76: Mise à disposition du fichier d'alimentation de Magnitude sur le drive pour les régions | E76: =IF(G76="J",D76,WORKDAY(D$53,MID(G76,2,3),Feuil1!D$2:D$14)) -> 46268 | F76: Matin | G76: J+3
A77: Campagne Fournisseurs Virements Tiers Express | E77: =IF(G77="J",D77,WORKDAY(D$53,MID(G77,2,3),Feuil1!D$2:D$14)) -> 46268 | F77: Nuit | G77: J+3
B78: Incorporation des écritures à contrepassation sur mois suivant (2ème vendredi de chaque mois) | E78: 46276 | F78: Nuit
C79: Mise à disposition des échéanciers provisoires GROUPE sur vos clés régions | E79: =IF(G79="J",D79,WORKDAY(D$53,MID(G79,2,3),Feuil1!D$2:D$14)) -> 46279 | F79: Matin | G79: J+10
A80: Validation de l'échéancier GROUPE + Envoi des ordres de virements à CDPG + Envoi des avis de virements par mail aux Frs | E80: =IF(G80="J",D80,WORKDAY(D$53,MID(G80,2,3),Feuil1!D$2:D$14)) -> 46279 | F80: Nuit | G80: J+10
B81: PO Fermeture automatique des commandes (15 du mois) | E81: 46280 | F81: Nuit
C82: Mise à disposition des commandes fermées dans le drive pour les régions | E82: =E81+1 -> 46281 | F82: Matin
C83: Envoi du mail de confirmation des virements fournisseurs GROUPE | E83: =IF(G83="J",D83,WORKDAY(D$53,MID(G83,2,3),Feuil1!D$2:D$14)) -> 46280 | F83: Matin | G83: J+11
B84: Incorporation des encaissements suite à échéancier Groupe | E84: =IF(G84="J",D84,WORKDAY(D$53,MID(G84,2,3),Feuil1!D$2:D$14)) -> 46280 | F84: Nuit | G84: J+11
C85: Envoi par mail des encaissements partiellement lettrés suite passage Intra Groupe | E85: =E84+1 -> 46281 | F85: Matin | G85: J+12

Sheet JUILLET 2026
A1: CALENDRIER CLOTURE JUILLET 2026
A2: ARRETE | B2: TRAITEMENT | C2: RESTITUTION | D2: Date de Référence J
A3: Date limite de remontée des PV pour mise en service des investissements | E3: =IF(G3="J",D3,WORKDAY(D$53,MID(G3,2,3),Feuil1!D$2:D$14)) -> 46224 | F3: Matin | G3: J-8
A4: Campagne Fournisseurs Virements Tiers Express | E4: =IF(G4="J",D4,WORKDAY(D$53,MID(G4,2,3),Feuil1!D$2:D$14)) -> 46224 | F4: Nuit | G4: J-8
A5: Premiers relevés de compteurs et de stocks | E5: =IF(G5="J",D5,WORKDAY(D$53,MID(G5,2,3),Feuil1!D$2:D$14)) -> 46225 | F5: Matin | G5: J-7
A6: Campagne Fournisseurs Virements Tiers Express | E6: =IF(G6="J",D6,WORKDAY(D$53,MID(G6,2,3),Feuil1!D$2:D$14)) -> 46225 | F6: Nuit | G6: J-7
B7: Incorporation en comptabilité des écritures GL de paie | E7: =IF(G7="J",D7,WORKDAY(D$53,MID(G7,2,3),Feuil1!D$2:D$14)) -> 46225 | F7: Nuit | G7: J-7
A8: Campagne Fournisseurs Virements Tiers Express | E8: =IF(G8="J",D8,WORKDAY(D$53,MID(G8,2,3),Feuil1!D$2:D$14)) -> 46226 | F8: Nuit | G8: J-6
A9: ARCAS | B9: Envoi à la compta Siège du fichier PROGEFI par le service Trésorerie incluant les remarques des Uos | E9: =IF(G9="J",D9,WORKDAY(D$53,MID(G9,2,3),Feuil1!D$2:D$14)) -> 46227 | F9: Matin | G9: J-5
A10: Fermeture du livre comptable FA | E10: =IF(G10="J",D10,WORKDAY(D$53,MID(G10,2,3),Feuil1!D$2:D$14)) -> 46227 | F10: Soir | G10: J-5
B11: Premier passage des abonnements GL dans Oracle | E11: =IF(G11="J",D11,WORKDAY(D$53,MID(G11,2,3),Feuil1!D$2:D$14)) -> 46227 | F11: Nuit | G11: J-5
B12: Incorporation des écritures d'amortissements | E12: =IF(G12="J",D12,WORKDAY(D$53,MID(G12,2,3),Feuil1!D$2:D$14)) -> 46227 | F12: Nuit | G12: J-5
B13: Incorporation en comptabilité des écritures GL et provisions DACAR | E13: =IF(G13="J",D13,WORKDAY(D$53,MID(G13,2,3),Feuil1!D$2:D$14)) -> 46227 | F13: Nuit | G13: J-5
A14: Campagne Fournisseurs Virements Tiers Express | E14: =IF(G14="J",D14,WORKDAY(D$53,MID(G14,2,3),Feuil1!D$2:D$14)) -> 46227 | F14: Nuit | G14: J-5
A15: Date limite d'intégration des factures de carburant et péages (DACAR) | E15: =IF(G15="J",D15,WORKDAY(D$53,MID(G15,2,3),Feuil1!D$2:D$14)) -> 46230 | F15: Journée | G15: J-4
A16: CALLISTO | B16: Derniers retours des Uos (mise à jour navettes : subventions, exceptions) et remarques sur traitement M-1 | E16: =IF(G16="J",D16,WORKDAY(D$53,MID(G16,2,3),Feuil1!D$2:D$14)) -> 46230 | F16: Soir | G16: J-4
A17: ARCAS | B17: Traitement ARCAS pour incorporation des écritures d'abonnement | E17: =IF(G17="J",D17,WORKDAY(D$53,MID(G17,2,3),Feuil1!D$2:D$14)) -> 46230 | F17: Soir | G17: J-4
A18: Dernières transmissions des heures de M.O. | E18: =IF(G18="J",D18,WORKDAY(D$53,MID(G18,2,3),Feuil1!D$2:D$14)) -> 46230 | F18: Soir | G18: J-4
A19: Dernières saisies et validation des relevés de compteur et de stocks et des livraisons | E19: =IF(G19="J",D19,WORKDAY(D$53,MID(G19,2,3),Feuil1!D$2:D$14)) -> 46230 | F19: Soir | G19: J-4
A20: Campagne Fournisseurs Virements NDF Employé | E20: =IF(G20="J",D20,WORKDAY(D$53,MID(G20,2,3),Feuil1!D$2:D$14)) -> 46230 | F20: Nuit | G20: J-4
A21: Campagne Fournisseurs Virements Tiers Express | E21: =IF(G21="J",D21,WORKDAY(D$53,MID(G21,2,3),Feuil1!D$2:D$14)) -> 46230 | F21: Nuit | G21: J-4
B22: Second passage des abonnements GL dans Oracle | E22: =IF(G22="J",D22,WORKDAY(D$53,MID(G22,2,3),Feuil1!D$2:D$14)) -> 46230 | F22: Nuit | G22: J-4
B23: Calcul de la M.O. au THO (VACHE) | E23: =IF(G23="J",D23,WORKDAY(D$53,MID(G23,2,3),Feuil1!D$2:D$14)) -> 46230 | F23: Nuit | G23: J-4
A24: CALLISTO | B24: Traitement CALLISTO et incorporation des écritures IFRS + envoi fichiers justificatifs aux Uos | E24: =IF(G24="J",D24,WORKDAY(D$53,MID(G24,2,3),Feuil1!D$2:D$14)) -> 46231 | F24: Soir | G24: J-3
A25: ARCAS | B25: Traitement ARCAS et incorporation des écritures IFRS + envoi fichiers justificatifs aux Uos | E25: =IF(G25="J",D25,WORKDAY(D$53,MID(G25,2,3),Feuil1!D$2:D$14)) -> 46231 | F25: Soir | G25: J-3
A26: Arrêté ventes travaux (CITY) | E26: =IF(G26="J",D26,WORKDAY(D$53,MID(G26,2,3),Feuil1!D$2:D$14)) -> 46231 | F26: Soir | G26: J-3
A27: Délai pour la clôture des taches GT,GX et GS | E27: =IF(G27="J",D27,WORKDAY(D$53,MID(G27,2,3),Feuil1!D$2:D$14)) -> 46231 | F27: Soir | G27: J-3
A28: Arrêté ventes exploitation | E28: =IF(G28="J",D28,WORKDAY(D$53,MID(G28,2,3),Feuil1!D$2:D$14)) -> 46231 | F28: Soir | G28: J-3
A29: Arrêté de saisie des factures Open Portal Campus | E29: =IF(G29="J",D29,WORKDAY(D$53,MID(G29,2,3),Feuil1!D$2:D$14)) -> 46231 | F29: Soir | G29: J-3
B30: Calcul des PAR CID | E30: =IF(G30="J",D30,WORKDAY(D$53,MID(G30,2,3),Feuil1!D$2:D$14)) -> 46231 | F30: Soir | G30: J-3
A31: Arrêté de saisie des factures energies | E31: =IF(G31="J",D31,WORKDAY(D$53,MID(G31,2,3),Feuil1!D$2:D$14)) -> 46231 | F31: Soir | G31: J-3
A32: Campagne Fournisseurs Virements Tiers Express | E32: =IF(G32="J",D32,WORKDAY(D$53,MID(G32,2,3),Feuil1!D$2:D$14)) -> 46231 | F32: Nuit | G32: J-3
B33: Refacturation intra-groupe premier traitement | E33: =IF(G33="J",D33,WORKDAY(D$53,MID(G33,2,3),Feuil1!D$2:D$14)) -> 46231 | F33: Nuit | G33: J-3
B34: Dernier passage des abonnements GL dans Oracle | E34: =IF(G34="J",D34,WORKDAY(D$53,MID(G34,2,3),Feuil1!D$2:D$14)) -> 46231 | F34: Nuit | G34: J-3
B35: Incorporation des écritures de M.O. | E35: =IF(G35="J",D35,WORKDAY(D$53,MID(G35,2,3),Feuil1!D$2:D$14)) -> 46231 | F35: Nuit | G35: J-3
B36: Traitement PIRENE (calcul des CAP, valorisation des stocks, ventes) | E36: =IF(G36="J",D36,WORKDAY(D$53,MID(G36,2,3),Feuil1!D$2:D$14)) -> 46231 | F36: Nuit | G36: J-3
B37: Calcul des CAP Gaz, Chaleur et électricité CELERIS | E37: =IF(G37="J",D37,WORKDAY(D$53,MID(G37,2,3),Feuil1!D$2:D$14)) -> 46231 | F37: Nuit | G37: J-3
C38: Mise à disposition des états de REFAC au format PDF sur le drive pour les régions | E38: =IF(G38="J",D38,WORKDAY(D$53,MID(G38,2,3),Feuil1!D$2:D$14)) -> 46232 | F38: Matin | G38: J-2
A39: Modification manuelle des PAR Exploitation mensuels CID et CAP Céleris | E39: =IF(G39="J",D39,WORKDAY(D$53,MID(G39,2,3),Feuil1!D$2:D$14)) -> 46232 | F39: Journée | G39: J-2
B40: Génération des écritures des PAR Exploitation mensuels CID | E40: =IF(G40="J",D40,WORKDAY(D$53,MID(G40,2,3),Feuil1!D$2:D$14)) -> 46232 | F40: 17H | G40: J-2
B41: Génération des écritures de CAP CELERIS | E41: =IF(G41="J",D41,WORKDAY(D$53,MID(G41,2,3),Feuil1!D$2:D$14)) -> 46232 | F41: 17H | G41: J-2
B42: Incorporation des écritures de PAR Exploitation mensuels CID | E42: =IF(G42="J",D42,WORKDAY(D$53,MID(G42,2,3),Feuil1!D$2:D$14)) -> 46232 | F42: Nuit | G42: J-2
B43: Incorporation des écritures PIRENE (calcul des CAP, valorisation des stocks, ventes) | E43: =IF(G43="J",D43,WORKDAY(D$53,MID(G43,2,3),Feuil1!D$2:D$14)) -> 46232 | F43: Nuit | G43: J-2
B44: Incorporation des écritures de CAP Gaz, Chaleur et électricité CELERIS | E44: =IF(G44="J",D44,WORKDAY(D$53,MID(G44,2,3),Feuil1!D$2:D$14)) -> 46232 | F44: Nuit | G44: J-2
A45: Campagne Fournisseurs Virements Tiers Express | E45: =IF(G45="J",D45,WORKDAY(D$53,MID(G45,2,3),Feuil1!D$2:D$14)) -> 46232 | F45: Nuit | G45: J-2
B46: Refacturation intra-groupe Deuxième traitement | E46: =IF(G46="J",D46,WORKDAY(D$53,MID(G46,2,3),Feuil1!D$2:D$14)) -> 46232 | F46: Nuit | G46: J-2
C47: Mise disposition du fichier Harry Energy | E47: =IF(G47="J",D47,WORKDAY(D$53,MID(G47,2,3),Feuil1!D$2:D$14)) -> 46232 | F47: Nuit | G47: J-2
C48: Mise à disposition des états de REFAC au format PDF sur le drive pour les régions | E48: =IF(G48="J",D48,WORKDAY(D$53,MID(G48,2,3),Feuil1!D$2:D$14)) -> 46233 | F48: Matin | G48: J-1
B49: Fermeture automatique des commandes liées aux factures intra groupe CITY du mois | E49: =IF(G49="J",D49,WORKDAY(D$53,MID(G49,2,3),Feuil1!D$2:D$14)) -> 46233 | F49: Matin | G49: J-1
A50: Campagne Fournisseurs Virements Tiers Express | E50: =IF(G50="J",D50,WORKDAY(D$53,MID(G50,2,3),Feuil1!D$2:D$14)) -> 46233 | F50: Nuit | G50: J-1
B51: Refacturation intra-groupe Troisième traitement | E51: =IF(G51="J",D51,WORKDAY(D$53,MID(G51,2,3),Feuil1!D$2:D$14)) -> 46233 | F51: Nuit | G51: J-1
C52: Mise à disposition des états de REFAC au format PDF sur le drive pour les régions | D52: 46234 | E52: =IF(G52="J",D52,WORKDAY(D$53,MID(G52,2,3),Feuil1!D$2:D$14)) -> 46234 | F52: Matin | G52: J
A53: FERMETURE DE L'APPLICATION - CLOTURE PROVISOIRE GL - DEFINITIVES : AP - AR - PO | D53: 46234 | E53: =IF(G53="J",D53,WORKDAY(D$53,MID(G53,2,3),Feuil1!D$2:D$14)) -> 46234 | F53: Nuit | G53: J
B54: Refacturation intra-groupe (dernier passage) | D54: 46234 | E54: =IF(G54="J",D54,WORKDAY(D$53,MID(G54,2,3),Feuil1!D$2:D$14)) -> 46234 | F54: Nuit | G54: J
B55: Calcul des CAP fournisseurs et incorporation des écritures | D55: 46234 | E55: =IF(G55="J",D55,WORKDAY(D$53,MID(G55,2,3),Feuil1!D$2:D$14)) -> 46234 | F55: Nuit | G55: J
B56: Calcul des CAP spécifiques aux contrats de sous traitance et incorporation des écritures | D56: 46234 | E56: =IF(G56="J",D56,WORKDAY(D$53,MID(G56,2,3),Feuil1!D$2:D$14)) -> 46234 | F56: Nuit | G56: J
B57: Calcul et écriture des TEC et PCA (codes R) travaux en cours - produits constatés d'avance | D57: 46234 | E57: =IF(G57="J",D57,WORKDAY(D$53,MID(G57,2,3),Feuil1!D$2:D$14)) -> 46234 | F57: Nuit | G57: J
B58: Calcul et écriture des charges d'avance sur sinistres | D58: 46234 | E58: =IF(G58="J",D58,WORKDAY(D$53,MID(G58,2,3),Feuil1!D$2:D$14)) -> 46234 | F58: Nuit | G58: J
B59: Equilibrage comptable par centre de gestion | D59: 46234 | E59: =IF(G59="J",D59,WORKDAY(D$53,MID(G59,2,3),Feuil1!D$2:D$14)) -> 46234 | F59: Nuit | G59: J
C60: Mise à disposition des états de REFAC au format PDF sur le drive pour les régions | E60: =IF(G60="J",D60,WORKDAY(D$53,MID(G60,2,3),Feuil1!D$2:D$14)) -> 46237 | F60: Matin | G60: J+1
C61: Mise à disposition des états de TVA (AP, AR) sur le drive pour les régions | E61: =IF(G61="J",D61,WORKDAY(D$53,MID(G61,2,3),Feuil1!D$2:D$14)) -> 46237 | F61: Matin | G61: J+1
C62: Mise à disposition des états CAP PO et CAP SSTR sur le drive pour les régions | E62: =IF(G62="J",D62,WORKDAY(D$53,MID(G62,2,3),Feuil1!D$2:D$14)) -> 46237 | F62: Matin | G62: J+1
B63: Imputation (posting) des écritures GL saisies dans la matinée | E63: =IF(G63="J",D63,WORKDAY(D$53,MID(G63,2,3),Feuil1!D$2:D$14)) -> 46237 | F63: 13H | G63: J+1
A64: Campagne Fournisseurs Virements NDF Employé | E64: =IF(G64="J",D64,WORKDAY(D$53,MID(G64,2,3),Feuil1!D$2:D$14)) -> 46237 | F64: Nuit | G64: J+1
A65: Campagne Fournisseurs Virements Tiers Express | E65: =IF(G65="J",D65,WORKDAY(D$53,MID(G65,2,3),Feuil1!D$2:D$14)) -> 46237 | F65: Nuit | G65: J+1
B66: Extourne des écritures de TEC et PCA travaux en cours - produits constatés d'avance | E66: =IF(G66="J",D66,WORKDAY(D$53,MID(G66,2,3),Feuil1!D$2:D$14)) -> 46237 | F66: Nuit | G66: J+1
B67: Extourne des écritures de charges d'avance sur sinistres | E67: =IF(G67="J",D67,WORKDAY(D$53,MID(G67,2,3),Feuil1!D$2:D$14)) -> 46237 | F67: Nuit | G67: J+1
B68: Imputation (posting) des écritures GL saisies dans la matinée | E68: =IF(G68="J",D68,WORKDAY(D$53,MID(G68,2,3),Feuil1!D$2:D$14)) -> 46238 | F68: 13H | G68: J+2
A69: CLOTURE DEFINITIVE DE GL | E69: =IF(G69="J",D69,WORKDAY(D$53,MID(G69,2,3),Feuil1!D$2:D$14)) -> 46238 | F69: Nuit | G69: J+2
B70: Equilibrage comptable par centre de gestion | E70: =IF(G70="J",D70,WORKDAY(D$53,MID(G70,2,3),Feuil1!D$2:D$14)) -> 46238 | F70: Nuit | G70: J+2
B71: Alimentation de la Garantie Totale | E71: =IF(G71="J",D71,WORKDAY(D$53,MID(G71,2,3),Feuil1!D$2:D$14)) -> 46238 | F71: Nuit | G71: J+2
A72: Campagne Fournisseurs Virements Tiers Express | E72: =IF(G72="J",D72,WORKDAY(D$53,MID(G72,2,3),Feuil1!D$2:D$14)) -> 46238 | F72: Nuit | G72: J+2
C73: Mise à disposition des états de TVA (GL) sur le drive pour les régions | E73: =IF(G73="J",D73,WORKDAY(D$53,MID(G73,2,3),Feuil1!D$2:D$14)) -> 46239 | F73: Matin | G73: J+3
C74: Mise à disposition des flux et soldes | E74: =IF(G74="J",D74,WORKDAY(D$53,MID(G74,2,3),Feuil1!D$2:D$14)) -> 46239 | F74: Matin | G74: J+3
C75: Mise à disposition de l'état de contrôle des retraitements IFRS | E75: =IF(G75="J",D75,WORKDAY(D$53,MID(G75,2,3),Feuil1!D$2:D$14)) -> 46239 | F75: Matin | G75: J+3
C76: Mise à disposition du fichier d'alimentation de Magnitude sur le drive pour les régions | E76: =IF(G76="J",D76,WORKDAY(D$53,MID(G76,2,3),Feuil1!D$2:D$14)) -> 46239 | F76: Matin | G76: J+3
A77: Campagne Fournisseurs Virements Tiers Express | E77: =IF(G77="J",D77,WORKDAY(D$53,MID(G77,2,3),Feuil1!D$2:D$14)) -> 46239 | F77: Nuit | G77: J+3
B78: Incorporation des écritures à contrepassation sur mois suivant (2ème vendredi de chaque mois) | E78: 46248 | F78: Nuit
C79: Mise à disposition des échéanciers provisoires GROUPE sur vos clés régions | E79: =IF(G79="J",D79,WORKDAY(D$53,MID(G79,2,3),Feuil1!D$2:D$14)) -> 46248 | F79: Matin | G79: J+10
A80: Validation de l'échéancier GROUPE + Envoi des ordres de virements à CDPG + Envoi des avis de virements par mail aux Frs | E80: =IF(G80="J",D80,WORKDAY(D$53,MID(G80,2,3),Feuil1!D$2:D$14)) -> 46248 | F80: Soir | G80: J+10
B81: PO Fermeture automatique des commandes (15 du mois) | E81: 46249 | F81: Nuit
C82: Mise à disposition des commandes fermées dans le drive pour les régions | E82: =IF(G82="J",D82,WORKDAY(D$53,MID(G82,2,3),Feuil1!D$2:D$14)) -> 46251 | F82: Matin | G82: J+11
C83: Envoi du mail de confirmation des virements fournisseurs GROUPE | E83: =IF(G83="J",D83,WORKDAY(D$53,MID(G83,2,3),Feuil1!D$2:D$14)) -> 46251 | F83: Matin | G83: J+11
B84: Incorporation des encaissements suite à échéancier Groupe | E84: =IF(G84="J",D84,WORKDAY(D$53,MID(G84,2,3),Feuil1!D$2:D$14)) -> 46251 | F84: Nuit | G84: J+11
C85: Envoi par mail des encaissements partiellement lettrés suite passage Intra Groupe | E85: =E84+1 -> 46252 | F85: Matin | G85: J+12

Sheet Feuil2
B2: CALENDRIER CLOTURE Juillet 2026
B3: Jour | E3: Jalon | F3: Astreinte | G3: Cockpit
B4: Vendredi 24 Aout | C4: Nuit | D4: J-5 | E4: Cloture FA
B5: Vendredi 31 Aout | C5: Nuit | D5: J | E5: Cloture provisoire | F5: Oui (CtrlM)
B6: Lundi 03 Aout | C6: Matin | D6: J+1 | G6: 8H30
B7: 46267 | C7: Nuit | D7: J+2 | E7: Cloture définitive | F7: Oui (CtrlM)
B8: Mercredi 05 Aout | C8: Matin | D8: J+3 | G8: 8H30

Sheet SEPTEMBRE 2026
A1: CALENDRIER CLOTURE SEPTEMBRE 2026
A2: ARRETE | B2: TRAITEMENT | C2: RESTITUTION | D2: Date de Référence J
A3: Date limite de remontée des PV pour mise en service des investissements | E3: =IF(G3="J",D3,WORKDAY(D$56,MID(G3,2,3),Feuil1!D$2:D$14)) -> 46283 | F3: Matin | G3: J-8
A4: Campagne Fournisseurs Virements Tiers Express | E4: =IF(G4="J",D4,WORKDAY(D$56,MID(G4,2,3),Feuil1!D$2:D$14)) -> 46283 | F4: Nuit | G4: J-8
A5: Premiers relevés de compteurs et de stocks | E5: =IF(G5="J",D5,WORKDAY(D$56,MID(G5,2,3),Feuil1!D$2:D$14)) -> 46286 | F5: Matin | G5: J-7
A6: Campagne Fournisseurs Virements NDF Employé | E6: =IF(G6="J",D6,WORKDAY(D$56,MID(G6,2,3),Feuil1!D$2:D$14)) -> 46286 | F6: Nuit | G6: J-7
A7: Campagne Fournisseurs Virements Tiers Express | E7: =IF(G7="J",D7,WORKDAY(D$56,MID(G7,2,3),Feuil1!D$2:D$14)) -> 46286 | F7: Nuit | G7: J-7
A8: Campagne Fournisseurs Virements Tiers Express | E8: =IF(G8="J",D8,WORKDAY(D$56,MID(G8,2,3),Feuil1!D$2:D$14)) -> 46287 | F8: Nuit | G8: J-6
B9: Incorporation en comptabilité des écritures GL de paie | E9: =IF(G9="J",D9,WORKDAY(D$56,MID(G9,2,3),Feuil1!D$2:D$14)) -> 46288 | F9: Nuit | G9: J-5
C10: Campagne Fournisseurs TIERS FDM - Mise à disposition des échéanciers provisoires | E10: =IF(G10="J",D10,WORKDAY(D$56,MID(G10,2,3),Feuil1!D$2:D$14)) -> 46288 | F10: Matin | G10: J-5
A11: ARCAS | B11: Envoi à la compta Siège du fichier PROGEFI par le service Trésorerie incluant les remarques des Uos | E11: =IF(G11="J",D11,WORKDAY(D$56,MID(G11,2,3),Feuil1!D$2:D$14)) -> 46288 | F11: Matin | G11: J-5
A12: Fermeture du livre comptable FA | E12: =IF(G12="J",D12,WORKDAY(D$56,MID(G12,2,3),Feuil1!D$2:D$14)) -> 46288 | F12: Soir | G12: J-5
B13: Premier passage des abonnements GL dans Oracle | E13: =IF(G13="J",D13,WORKDAY(D$56,MID(G13,2,3),Feuil1!D$2:D$14)) -> 46288 | F13: Nuit | G13: J-5
B14: Incorporation des écritures d'amortissements | E14: =IF(G14="J",D14,WORKDAY(D$56,MID(G14,2,3),Feuil1!D$2:D$14)) -> 46288 | F14: Nuit | G14: J-5
B15: Incorporation en comptabilité des écritures GL et provisions DACAR | E15: =IF(G15="J",D15,WORKDAY(D$56,MID(G15,2,3),Feuil1!D$2:D$14)) -> 46288 | F15: Nuit | G15: J-5
A16: Campagne Fournisseurs TIERS FDM - Mise à disposition des pupitres et envoi du mail de Projection | E16: =IF(G16="J",D16,WORKDAY(D$56,MID(G16,2,3),Feuil1!D$2:D$14)) -> 46289 | F16: Matin | G16: J-4
A17: Date limite d'intégration des factures de carburant et péages (DACAR) | E17: =IF(G17="J",D17,WORKDAY(D$56,MID(G17,2,3),Feuil1!D$2:D$14)) -> 46289 | F17: Journée | G17: J-4
A18: CALLISTO | B18: Derniers retours des Uos (mise à jour navettes : subventions, exceptions) et remarques sur traitement M-1 | E18: =IF(G18="J",D18,WORKDAY(D$56,MID(G18,2,3),Feuil1!D$2:D$14)) -> 46289 | F18: Soir | G18: J-4
A19: ARCAS | B19: Traitement ARCAS pour incorporation des écritures d'abonnement | E19: =IF(G19="J",D19,WORKDAY(D$56,MID(G19,2,3),Feuil1!D$2:D$14)) -> 46289 | F19: Soir | G19: J-4
A20: Dernières transmissions des heures de M.O. | E20: =IF(G20="J",D20,WORKDAY(D$56,MID(G20,2,3),Feuil1!D$2:D$14)) -> 46289 | F20: Soir | G20: J-4
A21: Dernières saisies et validation des relevés de compteur et de stocks et des livraisons | E21: =IF(G21="J",D21,WORKDAY(D$56,MID(G21,2,3),Feuil1!D$2:D$14)) -> 46289 | F21: Soir | G21: J-4
A22: Validation de l'échéancier TIERS FDM + Envoi des ordres de virements à CDPG + Envoi des avis de virements par mail aux Frs | E22: =IF(G22="J",D22,WORKDAY(D$56,MID(G22,2,3),Feuil1!D$2:D$14)) -> 46289 | F22: Soir | G22: J-4
B23: Second passage des abonnements GL dans Oracle | E23: =IF(G23="J",D23,WORKDAY(D$56,MID(G23,2,3),Feuil1!D$2:D$14)) -> 46289 | F23: Nuit | G23: J-4
B24: Calcul de la M.O. au THO (VACHE) | E24: =IF(G24="J",D24,WORKDAY(D$56,MID(G24,2,3),Feuil1!D$2:D$14)) -> 46289 | F24: Nuit | G24: J-4
C25: Envoi du mail de confirmation des virements TIERS FDM | E25: =IF(G25="J",D25,WORKDAY(D$56,MID(G25,2,3),Feuil1!D$2:D$14)) -> 46290 | F25: Matin | G25: J-3
A26: CALLISTO | B26: Traitement CALLISTO et incorporation des écritures IFRS + envoi fichiers justificatifs aux Uos | E26: =IF(G26="J",D26,WORKDAY(D$56,MID(G26,2,3),Feuil1!D$2:D$14)) -> 46290 | F26: Soir | G26: J-3
A27: ARCAS | B27: Traitement ARCAS et incorporation des écritures IFRS + envoi fichiers justificatifs aux Uos | E27: =IF(G27="J",D27,WORKDAY(D$56,MID(G27,2,3),Feuil1!D$2:D$14)) -> 46290 | F27: Soir | G27: J-3
A28: Arrêté ventes travaux (CITY) | E28: =IF(G28="J",D28,WORKDAY(D$56,MID(G28,2,3),Feuil1!D$2:D$14)) -> 46290 | F28: Soir | G28: J-3
A29: Délai pour la clôture des taches GT,GX et GS | E29: =IF(G29="J",D29,WORKDAY(D$56,MID(G29,2,3),Feuil1!D$2:D$14)) -> 46290 | F29: Soir | G29: J-3
A30: Arrêté ventes exploitation | E30: =IF(G30="J",D30,WORKDAY(D$56,MID(G30,2,3),Feuil1!D$2:D$14)) -> 46290 | F30: Soir | G30: J-3
A31: Arrêté de saisie des factures Open Portal Campus | E31: =IF(G31="J",D31,WORKDAY(D$56,MID(G31,2,3),Feuil1!D$2:D$14)) -> 46290 | F31: Soir | G31: J-3
B32: Calcul des PAR CID | E32: =IF(G32="J",D32,WORKDAY(D$56,MID(G32,2,3),Feuil1!D$2:D$14)) -> 46290 | F32: Soir | G32: J-3
A33: Arrêté de saisie des factures energies | E33: =IF(G33="J",D33,WORKDAY(D$56,MID(G33,2,3),Feuil1!D$2:D$14)) -> 46290 | F33: Soir | G33: J-3
A34: Campagne Fournisseurs Virements Tiers Express | E34: =IF(G34="J",D34,WORKDAY(D$56,MID(G34,2,3),Feuil1!D$2:D$14)) -> 46290 | F34: Nuit | G34: J-3
B35: Refacturation intra-groupe premier traitement | E35: =IF(G35="J",D35,WORKDAY(D$56,MID(G35,2,3),Feuil1!D$2:D$14)) -> 46290 | F35: Nuit | G35: J-3
B36: Dernier passage des abonnements GL dans Oracle | E36: =IF(G36="J",D36,WORKDAY(D$56,MID(G36,2,3),Feuil1!D$2:D$14)) -> 46290 | F36: Nuit | G36: J-3
B37: Incorporation des écritures de M.O. | E37: =IF(G37="J",D37,WORKDAY(D$56,MID(G37,2,3),Feuil1!D$2:D$14)) -> 46290 | F37: Nuit | G37: J-3
B38: Traitement PIRENE (calcul des CAP, valorisation des stocks, ventes) | E38: =IF(G38="J",D38,WORKDAY(D$56,MID(G38,2,3),Feuil1!D$2:D$14)) -> 46290 | F38: Nuit | G38: J-3
B39: Calcul des CAP Gaz, Chaleur et électricité CELERIS | E39: =IF(G39="J",D39,WORKDAY(D$56,MID(G39,2,3),Feuil1!D$2:D$14)) -> 46290 | F39: Nuit | G39: J-3
C40: Mise à disposition des états de REFAC au format PDF sur le drive pour les régions | E40: =IF(G40="J",D40,WORKDAY(D$56,MID(G40,2,3),Feuil1!D$2:D$14)) -> 46293 | F40: Matin | G40: J-2
A41: Modification manuelle des PAR Exploitation mensuels CID et CAP Céleris | E41: =IF(G41="J",D41,WORKDAY(D$56,MID(G41,2,3),Feuil1!D$2:D$14)) -> 46293 | F41: Journée | G41: J-2
B42: Génération des écritures des PAR Exploitation mensuels CID | E42: =IF(G42="J",D42,WORKDAY(D$56,MID(G42,2,3),Feuil1!D$2:D$14)) -> 46293 | F42: 17H | G42: J-2
B43: Génération des écritures de CAP CELERIS | E43: =IF(G43="J",D43,WORKDAY(D$56,MID(G43,2,3),Feuil1!D$2:D$14)) -> 46293 | F43: 17H | G43: J-2
B44: Incorporation des écritures de PAR Exploitation mensuels CID | E44: =IF(G44="J",D44,WORKDAY(D$56,MID(G44,2,3),Feuil1!D$2:D$14)) -> 46293 | F44: Nuit | G44: J-2
B45: Incorporation des écritures PIRENE (calcul des CAP, valorisation des stocks, ventes) | E45: =IF(G45="J",D45,WORKDAY(D$56,MID(G45,2,3),Feuil1!D$2:D$14)) -> 46293 | F45: Nuit | G45: J-2
B46: Incorporation des écritures de CAP Gaz, Chaleur et électricité CELERIS | E46: =IF(G46="J",D46,WORKDAY(D$56,MID(G46,2,3),Feuil1!D$2:D$14)) -> 46293 | F46: Nuit | G46: J-2
A47: Campagne Fournisseurs Virements NDF Employé | E47: =IF(G47="J",D47,WORKDAY(D$56,MID(G47,2,3),Feuil1!D$2:D$14)) -> 46293 | F47: Nuit | G47: J-2
A48: Campagne Fournisseurs Virements Tiers Express | E48: =IF(G48="J",D48,WORKDAY(D$56,MID(G48,2,3),Feuil1!D$2:D$14)) -> 46293 | F48: Nuit | G48: J-2
B49: Refacturation intra-groupe Deuxième traitement | E49: =IF(G49="J",D49,WORKDAY(D$56,MID(G49,2,3),Feuil1!D$2:D$14)) -> 46293 | F49: Nuit | G49: J-2
C50: Mise disposition du fichier Harry Energy | E50: =IF(G50="J",D50,WORKDAY(D$56,MID(G50,2,3),Feuil1!D$2:D$14)) -> 46293 | F50: Nuit | G50: J-2
C51: Mise à disposition des états de REFAC au format PDF sur le drive pour les régions | E51: =IF(G51="J",D51,WORKDAY(D$56,MID(G51,2,3),Feuil1!D$2:D$14)) -> 46294 | F51: Matin | G51: J-1
B52: Fermeture automatique des commandes liées aux factures intra groupe CITY du mois | E52: =IF(G52="J",D52,WORKDAY(D$56,MID(G52,2,3),Feuil1!D$2:D$14)) -> 46294 | F52: Matin | G52: J-1
A53: Campagne Fournisseurs Virements Tiers Express | E53: =IF(G53="J",D53,WORKDAY(D$56,MID(G53,2,3),Feuil1!D$2:D$14)) -> 46294 | F53: Matin | G53: J-1
B54: Refacturation intra-groupe Troisième traitement | E54: =IF(G54="J",D54,WORKDAY(D$56,MID(G54,2,3),Feuil1!D$2:D$14)) -> 46294 | F54: Nuit | G54: J-1
C55: Mise à disposition des états de REFAC au format PDF sur le drive pour les régions | D55: 46295 | E55: =IF(G55="J",D55,WORKDAY(D$56,MID(G55,2,3),Feuil1!D$2:D$14)) -> 46295 | F55: Matin | G55: J
A56: FERMETURE DE L'APPLICATION - CLOTURE PROVISOIRE GL - DEFINITIVES : AP - AR - PO | D56: 46295 | E56: =IF(G56="J",D56,WORKDAY(D$56,MID(G56,2,3),Feuil1!D$2:D$14)) -> 46295 | F56: Nuit | G56: J
B57: Refacturation intra-groupe (dernier passage) | D57: 46295 | E57: =IF(G57="J",D57,WORKDAY(D$56,MID(G57,2,3),Feuil1!D$2:D$14)) -> 46295 | F57: Nuit | G57: J
B58: Calcul des CAP fournisseurs et incorporation des écritures | D58: 46295 | E58: =IF(G58="J",D58,WORKDAY(D$56,MID(G58,2,3),Feuil1!D$2:D$14)) -> 46295 | F58: Nuit | G58: J
B59: Calcul des CAP spécifiques aux contrats de sous traitance et incorporation des écritures | D59: 46295 | E59: =IF(G59="J",D59,WORKDAY(D$56,MID(G59,2,3),Feuil1!D$2:D$14)) -> 46295 | F59: Nuit | G59: J
B60: Calcul et écriture des TEC et PCA (codes R) travaux en cours - produits constatés d'avance | D60: 46295 | E60: =IF(G60="J",D60,WORKDAY(D$56,MID(G60,2,3),Feuil1!D$2:D$14)) -> 46295 | F60: Nuit | G60: J
B61: Calcul et écriture des charges d'avance sur sinistres | D61: 46295 | E61: =IF(G61="J",D61,WORKDAY(D$56,MID(G61,2,3),Feuil1!D$2:D$14)) -> 46295 | F61: Nuit | G61: J
B62: Equilibrage comptable par centre de gestion | D62: 46295 | E62: =IF(G62="J",D62,WORKDAY(D$56,MID(G62,2,3),Feuil1!D$2:D$14)) -> 46295 | F62: Nuit | G62: J
C63: Mise à disposition des états de REFAC au format PDF sur le drive pour les régions | E63: =IF(G63="J",D63,WORKDAY(D$56,MID(G63,2,3),Feuil1!D$2:D$14)) -> 46296 | F63: Matin | G63: J+1
C64: Mise à disposition des états de TVA (AP, AR) sur le drive pour les régions | E64: =IF(G64="J",D64,WORKDAY(D$56,MID(G64,2,3),Feuil1!D$2:D$14)) -> 46296 | F64: Matin | G64: J+1
C65: Mise à disposition des états CAP PO et CAP SSTR sur le drive pour les régions | E65: =IF(G65="J",D65,WORKDAY(D$56,MID(G65,2,3),Feuil1!D$2:D$14)) -> 46296 | F65: Matin | G65: J+1
B66: Imputation (posting) des écritures GL saisies dans la matinée | E66: =IF(G66="J",D66,WORKDAY(D$56,MID(G66,2,3),Feuil1!D$2:D$14)) -> 46296 | F66: 13H | G66: J+1
A67: Campagne Fournisseurs Virements Tiers Express | E67: =IF(G67="J",D67,WORKDAY(D$56,MID(G67,2,3),Feuil1!D$2:D$14)) -> 46296 | F67: Nuit | G67: J+1
B68: Extourne des écritures de TEC et PCA travaux en cours - produits constatés d'avance | E68: =IF(G68="J",D68,WORKDAY(D$56,MID(G68,2,3),Feuil1!D$2:D$14)) -> 46296 | F68: Nuit | G68: J+1
B69: Extourne des écritures de charges d'avance sur sinistres | E69: =IF(G69="J",D69,WORKDAY(D$56,MID(G69,2,3),Feuil1!D$2:D$14)) -> 46296 | F69: Nuit | G69: J+1
B70: Imputation (posting) des écritures GL saisies dans la matinée | E70: =IF(G70="J",D70,WORKDAY(D$56,MID(G70,2,3),Feuil1!D$2:D$14)) -> 46297 | F70: 13H | G70: J+2
A71: CLOTURE DEFINITIVE DE GL | E71: =IF(G71="J",D71,WORKDAY(D$56,MID(G71,2,3),Feuil1!D$2:D$14)) -> 46297 | F71: Nuit | G71: J+2
B72: Equilibrage comptable par centre de gestion | E72: =IF(G72="J",D72,WORKDAY(D$56,MID(G72,2,3),Feuil1!D$2:D$14)) -> 46297 | F72: Nuit | G72: J+2
B73: Alimentation de la Garantie Totale | E73: =IF(G73="J",D73,WORKDAY(D$56,MID(G73,2,3),Feuil1!D$2:D$14)) -> 46297 | F73: Nuit | G73: J+2
A74: Campagne Fournisseurs Virements Tiers Express | E74: =IF(G74="J",D74,WORKDAY(D$56,MID(G74,2,3),Feuil1!D$2:D$14)) -> 46297 | F74: Nuit | G74: J+2
C75: Mise à disposition des états de TVA (GL) sur le drive pour les régions | E75: =IF(G75="J",D75,WORKDAY(D$56,MID(G75,2,3),Feuil1!D$2:D$14)) -> 46300 | F75: Matin | G75: J+3
C76: Mise à disposition des flux et soldes | E76: =IF(G76="J",D76,WORKDAY(D$56,MID(G76,2,3),Feuil1!D$2:D$14)) -> 46300 | F76: Matin | G76: J+3
C77: Mise à disposition de l'état de contrôle des retraitements IFRS | E77: =IF(G77="J",D77,WORKDAY(D$56,MID(G77,2,3),Feuil1!D$2:D$14)) -> 46300 | F77: Matin | G77: J+3
C78: Mise à disposition du fichier d'alimentation de Magnitude sur le drive pour les régions | E78: =IF(G78="J",D78,WORKDAY(D$56,MID(G78,2,3),Feuil1!D$2:D$14)) -> 46300 | F78: Matin | G78: J+3
C79: Mise à disposition des Balances Clients et Fournisseurs au 30/09 sur le drive pour les régions | E79: =IF(G79="J",D79,WORKDAY(D$56,MID(G79,2,3),Feuil1!D$2:D$14)) -> 46300 | F79: Matin | G79: J+3
A80: Campagne Fournisseurs Virements NDF Employé | E80: =IF(G80="J",D80,WORKDAY(D$56,MID(G80,2,3),Feuil1!D$2:D$14)) -> 46300 | F80: Nuit | G80: J+3
A81: Campagne Fournisseurs Virements Tiers Express | E81: =IF(G81="J",D81,WORKDAY(D$56,MID(G81,2,3),Feuil1!D$2:D$14)) -> 46300 | F81: Nuit | G81: J+3
B82: Traitement de Surtaxe Communale | E82: =IF(G82="J",D82,WORKDAY(D$56,MID(G82,2,3),Feuil1!D$2:D$14)) -> 46303 | F82: Nuit | G82: J+6
C83: Mise à disposition des états de surtaxe communale sur le drive pour les régions | E83: =IF(G83="J",D83,WORKDAY(D$56,MID(G83,2,3),Feuil1!D$2:D$14)) -> 46304 | F83: Matin | G83: J+7
B84: Incorporation des écritures à contrepassation sur mois suivant (2ème vendredi de chaque mois) | E84: 46304 | F84: Nuit
C85: Mise à disposition des échéanciers provisoires GROUPE sur vos clés régions | E85: =IF(G85="J",D85,WORKDAY(D$56,MID(G85,2,3),Feuil1!D$2:D$14)) -> 46309 | F85: Matin | G85: J+10
A86: Validation de l'échéancier GROUPE + Envoi des ordres de virements à CDPG + Envoi des avis de virements par mail aux Frs | E86: =IF(G86="J",D86,WORKDAY(D$56,MID(G86,2,3),Feuil1!D$2:D$14)) -> 46309 | F86: Soir | G86: J+10
B87: PO Fermeture automatique des commandes (15 du mois) | E87: 46310 | F87: Nuit
C88: Mise à disposition des commandes fermées dans le drive pour les régions | E88: =E87+1 -> 46311 | F88: Matin
C89: Envoi du mail de confirmation des virements fournisseurs GROUPE | E89: =IF(G89="J",D89,WORKDAY(D$56,MID(G89,2,3),Feuil1!D$2:D$14)) -> 46310 | F89: Matin | G89: J+11
B90: Incorporation des encaissements suite à échéancier Groupe | E90: =IF(G90="J",D90,WORKDAY(D$56,MID(G90,2,3),Feuil1!D$2:D$14)) -> 46310 | F90: Nuit | G90: J+11
C91: Envoi par mail des encaissements partiellement lettrés suite passage Intra Groupe | E91: =IF(G91="J",D91,WORKDAY(D$56,MID(G91,2,3),Feuil1!D$2:D$14)) -> 46311 | F91: Matin | G91: J+12
